[
  {
    "text": "Amazon | Chik Shampoo, 650ml at 210\n\n🔗 https://tinyurl.com/28n8aoxa\n\n🛒 Deals by @hugediscountshop",
    "url": "https://tinyurl.com/28n8aoxa",
    "product_url": "https://www.amazon.in/dp/B093DH1CD8?th=1&tag=megadealind-21",
    "source": "megadealind",
    "image": "",
    "timestamp": "2026-04-18T07:15:52.911084+00:00"
  },
  {
    "text": "🔥🔥Crompton Dyna Ray 7W Round B22 LED Cool Day Light Pack of 4\n\n🎁 Deal Price : ₹188\n\n🔗 https://tinyurl.com/2y7cbp5m\n\n🛒 Deals by @hugediscountshop",
    "url": "https://tinyurl.com/2y7cbp5m",
    "product_url": "https://www.amazon.in/dp/B0B6FJWV8D?th=1&ck&tag=lootdealska02-21",
    "source": "Loot_Deals_Xpress",
    "image": "",
    "timestamp": "2026-04-18T07:15:36.977137+00:00"
  },
  {
    "text": "Amazon | Chik Shampoo, 650ml at 210\n\n🔗 https://tinyurl.com/28n8aoxa\n\n🛒 Deals by @hugediscountshop",
    "url": "https://tinyurl.com/28n8aoxa",
    "product_url": "https://www.amazon.in/dp/B093DH1CD8?th=1&ck&tag=lootdealska02-21",
    "source": "Loot_Deals_Xpress",
    "image": "",
    "timestamp": "2026-04-18T07:15:28.288675+00:00"
  },
  {
    "text": "Mivi 26W BT Soundbar at Rs.1399\n\n🔗 https://tinyurl.com/27q9fjdq\n\n🛒 Deals by @hugediscountshop",
    "url": "https://tinyurl.com/27q9fjdq",
    "product_url": "https://www.amazon.in/dp/B0F74T2V2C?th=1&ck&tag=lootdealska02-21",
    "source": "Loot_Deals_Xpress",
    "image": "",
    "timestamp": "2026-04-18T07:10:52.772387+00:00"
  },
  {
    "text": "AmazonBasics Gaming Headphone @637\n\n🔗 https://tinyurl.com/237nx62a\n\n🛒 Deals by @hugediscountshop",
    "url": "https://tinyurl.com/237nx62a",
    "product_url": "https://www.amazon.in/dp/B0DG2ZND2L?psc=1&th=1&ck&tag=lootdealska02-21",
    "source": "Loot_Deals_Xpress",
    "image": "",
    "timestamp": "2026-04-18T07:10:41.846369+00:00"
  },
  {
    "text": "62% off on - Livpure KoolBliss Neo Desert Cooler 70L |471 Sq. Ft. Area Coverage - Rs. 6799\n\n🔗 https://tinyurl.com/27bbbplt\n\n🛒 Deals by @hugediscountshop",
    "url": "https://tinyurl.com/27bbbplt",
    "product_url": "https://www.amazon.in/dp/B0GFWTHPQP?th=1&tag=desidimetelegram-21&ascsubtag=20260418cl2xr6ofg6ih",
    "source": "desidime",
    "image": "",
    "timestamp": "2026-04-18T07:01:23.388485+00:00"
  },
  {
    "text": "Amazon | PUMA Caps Starts @329\n\n🔗 https://tinyurl.com/2dz5ydo9\n\n🛒 Deals by @hugediscountshop",
    "url": "https://tinyurl.com/2dz5ydo9",
    "product_url": "https://www.amazon.in/s?k=puma%252Bcaps&rh=p_123%253A256097%252Cp_6%253AA1WYWER0W24N8S%257CA2SVCN105YZ7WG%257CA3L1OUG0B9LM6T%252Cp_n_pct-off-with-tax%253A2665402031&s=price-asc-rank&dc=&crid=1OXMRISNSCGKG&qid=1763393312&sprefix=puma%252Bcaps%252B%252Caps%252C280&ds=v1%253AoyDL0i3ihF22tY78C9O7pfVE74ciYdBuw7QmhJt5K%252Bo&ck&tag=lootdealska02-21",
    "source": "Loot_Deals_Xpress",
    "image": "",
    "timestamp": "2026-04-18T07:01:13.455215+00:00"
  },
  {
    "text": "LG Smart Choice, 322 L, 3 Star, Frost-Free Smart Inverter Double Door Refrigerator @27,990\n\nApply 2000 Off Coupon+ 7000 Off With HDFC Credit Card\n\n🔗 https://tinyurl.com/2cszqrqa\n\n🛒 Deals by @hugediscountshop",
    "url": "https://tinyurl.com/2cszqrqa",
    "product_url": "https://www.amazon.in/dp/B0C8NTDY55?ck&tag=lootdealska02-21",
    "source": "Loot_Deals_Xpress",
    "image": "",
    "timestamp": "2026-04-18T07:01:04.321337+00:00"
  },
  {
    "text": "Samsung 653 L, 3 Star, Frost Free, Double Door, Side By Side AI Enabled Smart Refrigerator @56,740\n\nApply 3000 Off Coupon+ 18250 Off With SBI Credit Card\n\n🔗 https://tinyurl.com/2anypm6s\n\n🛒 Deals by @hugediscountshop",
    "url": "https://tinyurl.com/2anypm6s",
    "product_url": "https://www.amazon.in/dp/B0BQC4Y4TP?ck&tag=lootdealska02-21",
    "source": "Loot_Deals_Xpress",
    "image": "",
    "timestamp": "2026-04-18T07:00:53.321176+00:00"
  },
  {
    "text": "Borosil Glider 1000W Dry Iron @551\n\n🔗 https://tinyurl.com/2b354qcm\n\n🛒 Deals by @hugediscountshop",
    "url": "https://tinyurl.com/2b354qcm",
    "product_url": "https://www.amazon.in/dp/B0CMZ8Z7HY?ck&tag=lootdealska02-21",
    "source": "Loot_Deals_Xpress",
    "image": "",
    "timestamp": "2026-04-18T07:00:43.110539+00:00"
  },
  {
    "text": "Zebronics Wireless Bluetooth Soundbar, 42 Watts, @1599\n\nApply 300 Off Coupon\n\n🔗 https://tinyurl.com/2bwh37wd\n\n🛒 Deals by @hugediscountshop",
    "url": "https://tinyurl.com/2bwh37wd",
    "product_url": "https://www.amazon.in/dp/B0FM43FR9D?ck&tag=lootdealska02-21",
    "source": "Loot_Deals_Xpress",
    "image": "",
    "timestamp": "2026-04-18T06:50:37.607788+00:00"
  },
  {
    "text": "Flipkart | 91% Off on Dubstep Pop 1210 Wireless Speaker At Rs.549\n\n🔗 https://tinyurl.com/2asbwgrn\n\n🛒 Deals by @hugediscountshop",
    "url": "https://tinyurl.com/2asbwgrn",
    "product_url": "https://linkredirect.in/visitretailer/2276?id=791399&shareid=ldnbeNr&dl=https%3A%2F%2Fwww.flipkart.com%2Fdubstep-pop-1210-wireless-speaker-16-hrs-playtime-52mm-dynamic-driver-tws-pairing-12-w-bluetooth%2Fp%2Fitm3dee3370c3cee%3Fpid%3DACCHC4HBP9DMS6HY&source=Default",
    "source": "megadealind",
    "image": "",
    "timestamp": "2026-04-18T06:45:34.753848+00:00"
  },
  {
    "text": "65% off on - L'OREAL PARIS Collagen Face Moisturizer, Skin Care, Day And Night Cream 1. 7 Oz. - Rs. 1291\n\n🔗 https://tinyurl.com/27f5zze6\n\n🛒 Deals by @hugediscountshop",
    "url": "https://tinyurl.com/27f5zze6",
    "product_url": "https://www.amazon.in/LOr%C3%A9al-Paris-Moisturizer-Anti-Aging-Non-Greasy/dp/B002JDUMFO?tag=desidimetelegram-21&ascsubtag=20260418cl581baaskpe",
    "source": "desidime",
    "image": "",
    "timestamp": "2026-04-18T06:40:48.491346+00:00"
  },
  {
    "text": "🔥🔥 Bajaj DMH 90 Neo 90L Desert Air Cooler for Home|For Larger Room\n\n🎁 Deal Price : ₹8,679\n\n💥 Bank Offer : ₹2,319 Off On SBI Credit Card EMI Txn\n\n🔗 https://tinyurl.com/27834h66\n\n🛒 Deals by @hugediscountshop",
    "url": "https://tinyurl.com/27834h66",
    "product_url": "https://www.amazon.in/dp/B08W29FFB9?ck&tag=lootdealska02-21",
    "source": "Loot_Deals_Xpress",
    "image": "",
    "timestamp": "2026-04-18T06:40:37.077581+00:00"
  },
  {
    "text": "Logitech MX Master 3S Wireless Bluetooth Mouse @ ₹7,999 \n\n🔗https://www.amazon.in/Logitech-Master-Mac-Ultra-Fast-Customization/dp/B0BGPV5BTN?pf_rd_r=QXDQEJG5WDMXJXDGTF5C&pf_rd_p=5fe84bca-b10d-4440-8a13-3b0ffdd77ad9&th=1&tag=lootdealska02-21\n\n❌Regular price @ ₹8,671\n\n🔗 https://tinyurl.com/23cjo63g\n\n🛒 Deals by @hugediscountshop",
    "url": "https://tinyurl.com/23cjo63g",
    "product_url": "ttps://www.amazon.in/Logitech-Master-Mac-Ultra-Fast-Customization/dp/B0BGPV5BTN?pf_rd_r=QXDQEJG5WDMXJXDGTF5C&pf_rd_p=5fe84bca-b10d-4440-8a13-3b0ffdd77ad9&th=1&tag=lootdealska02-21\n",
    "source": "Loot_Deals_Xpress",
    "image": "",
    "timestamp": "2026-04-18T06:35:34.954660+00:00"
  },
  {
    "text": "Havells 2-in-1 Convertible 80 L Desert Air Cooler for room @ ₹10,432 \n\n🔗https://www.amazon.in/Havells-Convertible-functionality-Air-Delivery-honeycomb/dp/B0DQKRHMHK?tag=lootdealska02-21\n\n❌Regular price @ ₹\n\n💡Flat ₹2,503 off with SBI EMI\n\n🔗 https://tinyurl.com/232v2cgh\n\n🛒 Deals by @hugediscountshop",
    "url": "https://tinyurl.com/232v2cgh",
    "product_url": "ttps://www.amazon.in/Havells-Convertible-functionality-Air-Delivery-honeycomb/dp/B0DQKRHMHK?tag=lootdealska02-21\n",
    "source": "Loot_Deals_Xpress",
    "image": "",
    "timestamp": "2026-04-18T06:35:28.960132+00:00"
  },
  {
    "text": "24 W Dual Car Charger @149\n\n🔗 https://tinyurl.com/2c9zqqh7\n\n🛒 Deals by @hugediscountshop",
    "url": "https://tinyurl.com/2c9zqqh7",
    "product_url": "https://www.amazon.in/dp/B08HRMS53Y?ck&tag=lootdealska02-21",
    "source": "Loot_Deals_Xpress",
    "image": "",
    "timestamp": "2026-04-18T06:25:49.499522+00:00"
  },
  {
    "text": "Kesh King Anti Hairfall Shampoo 1000 ml @389\n\n🔗 https://tinyurl.com/29gzp258\n\n🛒 Deals by @hugediscountshop",
    "url": "https://tinyurl.com/29gzp258",
    "product_url": "https://www.amazon.in/dp/B0B2R6WXGC?psc=1&th=1&ck&tag=lootdealska02-21",
    "source": "Loot_Deals_Xpress",
    "image": "",
    "timestamp": "2026-04-18T06:25:33.565126+00:00"
  },
  {
    "text": "@ 290/- APPLY COUPON\n\n🔗 https://tinyurl.com/26hanxbg\n\n🛒 Deals by @hugediscountshop",
    "url": "https://tinyurl.com/26hanxbg",
    "product_url": "https://www.amazon.in/dp/B0D9TR16ZJ?th=1&ck&tag=lootdealska02-21",
    "source": "Loot_Deals_Xpress",
    "image": "",
    "timestamp": "2026-04-18T06:10:52.590763+00:00"
  },
  {
    "text": "🔥🔥Parachute Advansed Jasmine Gold Non-Sticky Coconut Hair Oil, 600ml\n\n🎁 Deal Price : ₹194\n\n⚡⚡Apply 3% coupon (Prime Discount)\n\n🔗 https://tinyurl.com/29nj5haw\n\n🛒 Deals by @hugediscountshop",
    "url": "https://tinyurl.com/29nj5haw",
    "product_url": "https://www.amazon.in/dp/B0FY67CG6W?th=1&ck&tag=lootdealska02-21",
    "source": "Loot_Deals_Xpress",
    "image": "",
    "timestamp": "2026-04-18T06:05:35.608765+00:00"
  },
  {
    "text": "Amazon | Beardo Perfumes Upto 63% off Starts @188.\n\n👉https://www.amazon.in/s?s=price&hidden-keywords=B08NX1V7MC%7CB09N41G9Z1%7CB09V4ZRFPT%7CB096XV4HR4%7CB0BCKMZY1V%7CB0DHVRFN8V%7CB0DCZ458N4%7CB07XVQ1Q75%7CB0DR32JSJB%7CB0DNMYT371&&ck&tag=lootdealska02-21&\n\n🔗 ttps://www.amazon.in/s?s=price&hidden-keywords=B08NX1V7MC%7CB09N41G9Z1%7CB09V4ZRFPT%7CB096XV4HR4%7CB0BCKMZY1V%7CB0DHVRFN8V%7CB0DCZ458N4%7CB07XVQ1Q75%7CB0DR32JSJB%7CB0DNMYT371&&ck&tag=arusubh-21\n\n🛒 Deals by @hugediscountshop",
    "url": "ttps://www.amazon.in/s?s=price&hidden-keywords=B08NX1V7MC%7CB09N41G9Z1%7CB09V4ZRFPT%7CB096XV4HR4%7CB0BCKMZY1V%7CB0DHVRFN8V%7CB0DCZ458N4%7CB07XVQ1Q75%7CB0DR32JSJB%7CB0DNMYT371&&ck&tag=arusubh-21",
    "product_url": "ttps://www.amazon.in/s?s=price&hidden-keywords=B08NX1V7MC%7CB09N41G9Z1%7CB09V4ZRFPT%7CB096XV4HR4%7CB0BCKMZY1V%7CB0DHVRFN8V%7CB0DCZ458N4%7CB07XVQ1Q75%7CB0DR32JSJB%7CB0DNMYT371&&ck&tag=lootdealska02-21&",
    "source": "Loot_Deals_Xpress",
    "image": "",
    "timestamp": "2026-04-18T06:00:58.324523+00:00"
  },
  {
    "text": "Apply Rs.300 Coupon | Certified Organic A2 Gir Cow Ghee 500ml @ 769.\n\n🔗 https://tinyurl.com/25s3cbwo\n\n🛒 Deals by @hugediscountshop",
    "url": "https://tinyurl.com/25s3cbwo",
    "product_url": "https://www.amazon.in/dp/B0CZ9JGDCP?th=1&ck&tag=lootdealska02-21",
    "source": "Loot_Deals_Xpress",
    "image": "",
    "timestamp": "2026-04-18T06:00:52.287637+00:00"
  },
  {
    "text": "Whirlpool 1.5 Ton 3 Star 2026 Model @26839\n\nApply ₹250 Coupon + ₹3250 Off Via HDFC CC\n\n🔗 https://tinyurl.com/247uc7cb\n\n🛒 Deals by @hugediscountshop",
    "url": "https://tinyurl.com/247uc7cb",
    "product_url": "https://www.amazon.in/dp/B0GHQVN35Z?psc=1&ck&tag=lootdealska02-21",
    "source": "Loot_Deals_Xpress",
    "image": "",
    "timestamp": "2026-04-18T06:00:39.417091+00:00"
  },
  {
    "text": "Grab🔥\n\n250₹ coupon off\n\n1051₹\n\nFrench Connection Zest Apricot Color Round Dial Womens Analogue Watch \n\nOther colour costs more 🔥\n\n🔗 https://tinyurl.com/2dh4do75\n\n🛒 Deals by @hugediscountshop",
    "url": "https://tinyurl.com/2dh4do75",
    "product_url": "https://www.amazon.in/dp/B0D78MV7QS?ck&tag=lootdealska02-21",
    "source": "Loot_Deals_Xpress",
    "image": "",
    "timestamp": "2026-04-18T05:51:22.427428+00:00"
  },
  {
    "text": "58% off : Santoor Brightening Shower Gel 500ml @147\n\n🔗 https://tinyurl.com/28s7dj7y\n\n🛒 Deals by @hugediscountshop",
    "url": "https://tinyurl.com/28s7dj7y",
    "product_url": "https://www.amazon.in/dp/B0CQYG22TN?psc=1&th=1&ck&tag=lootdealska02-21",
    "source": "Loot_Deals_Xpress",
    "image": "",
    "timestamp": "2026-04-18T05:50:54.026755+00:00"
  },
  {
    "text": "🔥🔥DFC Element Aura Oak & White Side Table\n\n🎁 Deal Price : ₹999\n\n🔗 https://tinyurl.com/2yqgjnyt\n\n🛒 Deals by @hugediscountshop",
    "url": "https://tinyurl.com/2yqgjnyt",
    "product_url": "https://www.amazon.in/dp/B0BNBBCYCM?th=1&ck&tag=lootdealska02-21",
    "source": "Loot_Deals_Xpress",
    "image": "",
    "timestamp": "2026-04-18T05:50:41.336038+00:00"
  },
  {
    "text": "Garden Tools Set at Rs.287\n\n🔗 https://tinyurl.com/2yvyo7lu\n\n🛒 Deals by @hugediscountshop",
    "url": "https://tinyurl.com/2yvyo7lu",
    "product_url": "https://www.amazon.in/dp/B0FSD5F1DQ?th=1&tag=megadealind-21",
    "source": "megadealind",
    "image": "",
    "timestamp": "2026-04-18T05:45:30.920060+00:00"
  },
  {
    "text": "pTron Studio Evo 70hrs Playtime Wireless Over Ear Headphones ₹798🔥🔥\n\n🔗 https://tinyurl.com/22rdga69\n\n🛒 Deals by @hugediscountshop",
    "url": "https://tinyurl.com/22rdga69",
    "product_url": "https://www.amazon.in/dp/B0FGV2CNN5?ck&tag=lootdealska02-21",
    "source": "Loot_Deals_Xpress",
    "image": "",
    "timestamp": "2026-04-18T05:40:33.022484+00:00"
  },
  {
    "text": "Grab faast 🔥\n\n48,990₹\n\n2k off coupon\n\n🔗 https://tinyurl.com/2bbmux63\n\n🛒 Deals by @hugediscountshop",
    "url": "https://tinyurl.com/2bbmux63",
    "product_url": "https://www.amazon.in/dp/B0B8ZMLRH4?psc=1&ck&tag=lootdealska02-21",
    "source": "Loot_Deals_Xpress",
    "image": "",
    "timestamp": "2026-04-18T05:35:31.961312+00:00"
  },
  {
    "text": "Min. 2 Qnty | 73% Off : Dabur Charcoal Toothpaste (120g x 2) @99.\n\n🔗 https://tinyurl.com/2dngntqh\n\n🛒 Deals by @hugediscountshop",
    "url": "https://tinyurl.com/2dngntqh",
    "product_url": "https://www.amazon.in/dp/B0BQC6B15R?psc=1&ck&tag=lootdealska02-21",
    "source": "Loot_Deals_Xpress",
    "image": "",
    "timestamp": "2026-04-18T05:35:25.903375+00:00"
  },
  {
    "text": "65% Off : Dove Bath & Body Essentials Kit for ₹389.\n\n🔗 https://tinyurl.com/26s4mgbs\n\n🛒 Deals by @hugediscountshop",
    "url": "https://tinyurl.com/26s4mgbs",
    "product_url": "https://www.amazon.in/dp/B0FPQFP974?psc=1&th=1&tag=megadealind-21",
    "source": "megadealind",
    "image": "",
    "timestamp": "2026-04-18T05:31:39.107615+00:00"
  },
  {
    "text": "Nirlon Gas Compatible Nonstick Aluminium Deep Fry at 764\n\n🔗 https://tinyurl.com/25mzsbzd\n\n🛒 Deals by @hugediscountshop",
    "url": "https://tinyurl.com/25mzsbzd",
    "product_url": "https://www.amazon.in/dp/B094R6NC8H?psc=1&th=1&smid=AXOGFIT0PZZ7G&ck&tag=lootdealska02-21",
    "source": "Loot_Deals_Xpress",
    "image": "",
    "timestamp": "2026-04-18T05:31:14.783576+00:00"
  },
  {
    "text": "Body Wash Starts @96.\n\n🔗 https://tinyurl.com/274mvkzd\n\n🛒 Deals by @hugediscountshop",
    "url": "https://tinyurl.com/274mvkzd",
    "product_url": "https://www.amazon.in/s?k=Fiama&ck&tag=lootdealska02-21",
    "source": "Loot_Deals_Xpress",
    "image": "",
    "timestamp": "2026-04-18T05:31:01.998245+00:00"
  },
  {
    "text": "Dove Bath & Body Essentials Kit for ₹389.\n\n🔗 https://tinyurl.com/26s4mgbs\n\n🛒 Deals by @hugediscountshop",
    "url": "https://tinyurl.com/26s4mgbs",
    "product_url": "https://www.amazon.in/dp/B0FPQFP974?psc=1&th=1&ck&tag=lootdealska02-21",
    "source": "Loot_Deals_Xpress",
    "image": "",
    "timestamp": "2026-04-18T05:30:53.409161+00:00"
  },
  {
    "text": "Min. 2 Qnty | 73% Off : Dabur Charcoal Toothpaste (120g x 2) @99.\n\n🔗 https://tinyurl.com/2dngntqh\n\n🛒 Deals by @hugediscountshop",
    "url": "https://tinyurl.com/2dngntqh",
    "product_url": "https://www.amazon.in/dp/B0BQC6B15R?psc=1&smid=A15APWRK6P7LBV&ck&tag=lootdealska02-21",
    "source": "Loot_Deals_Xpress",
    "image": "",
    "timestamp": "2026-04-18T05:30:40.551267+00:00"
  },
  {
    "text": "Loot🚀🚀Dervin Premium Sunglasses Starts from @ ₹399\n\n🔗https://www.amazon.in/s?k=Dervin&i=apparel&rh=n%3A1571271031%2Cp_123%3A379523&dc=&ds=v1%3AIOGyxEfHNKq0GVs1MYCG3rawm7pt9%2FjChLLJ2Ov5k8g&crid=3C86PRFFRTN45&qid=1776488723&sprefix=dervin%20%2Capparel%2C464&tag=lootdealska02-21\n\n🔗 ps://www.amazon.in/s?k=Dervin&i=apparel&rh=n%3A1571271031%2Cp_123%3A379523&dc=&ds=v1%3AIOGyxEfHNKq0GVs1MYCG3rawm7pt9%2FjChLLJ2Ov5k8g&crid=3C86PRFFRTN45&qid=1776488723&sprefix=dervin%20%2Capparel%2C464&tag=arusubh-21\n\n🛒 Deals by @hugediscountshop",
    "url": "ps://www.amazon.in/s?k=Dervin&i=apparel&rh=n%3A1571271031%2Cp_123%3A379523&dc=&ds=v1%3AIOGyxEfHNKq0GVs1MYCG3rawm7pt9%2FjChLLJ2Ov5k8g&crid=3C86PRFFRTN45&qid=1776488723&sprefix=dervin%20%2Capparel%2C464&tag=arusubh-21",
    "product_url": "ps://www.amazon.in/s?k=Dervin&i=apparel&rh=n%3A1571271031%2Cp_123%3A379523&dc=&ds=v1%3AIOGyxEfHNKq0GVs1MYCG3rawm7pt9%2FjChLLJ2Ov5k8g&crid=3C86PRFFRTN45&qid=1776488723&sprefix=dervin%20%2Capparel%2C464&tag=lootdealska02-21",
    "source": "Loot_Deals_Xpress",
    "image": "",
    "timestamp": "2026-04-18T05:30:36.036826+00:00"
  },
  {
    "text": "Crompton Ozone Neo Desert Air Cooler, 95L \n\nApply 3% Off Coupon + ₹1973 Off With SBI CC No Cost EMI\n\n🔗 https://tinyurl.com/2yen3tyc\n\n🛒 Deals by @hugediscountshop",
    "url": "https://tinyurl.com/2yen3tyc",
    "product_url": "https://www.amazon.in/dp/B0GFCVGS1Z?tag=megadealind-21",
    "source": "megadealind",
    "image": "",
    "timestamp": "2026-04-18T05:25:31.330682+00:00"
  },
  {
    "text": "LOOOT @6998\n\nApply 3% Off Coupon + 1992 Off With SBI Card On 3 Month No Cost Emi\n\n🔗 https://tinyurl.com/2yen3tyc\n\n🛒 Deals by @hugediscountshop",
    "url": "https://tinyurl.com/2yen3tyc",
    "product_url": "https://www.amazon.in/dp/B0GFCVGS1Z?ck&tag=lootdealska02-21",
    "source": "Loot_Deals_Xpress",
    "image": "",
    "timestamp": "2026-04-18T05:20:28.875380+00:00"
  },
  {
    "text": "100% off on - Pepperfry - What The Fry Deals | Upto 100% off | + Delivery Chargers  - Rs. 1\n\n🔗 https://tinyurl.com/2bo69y2u\n\n🛒 Deals by @hugediscountshop",
    "url": "https://tinyurl.com/2bo69y2u",
    "product_url": "https://pepperfry.gotrackier.io/click?campaign_id=2&pub_id=10&p1=20260418clla91mabu55&source=198024&url=https%3A%2F%2Fwww.pepperfry.com%2F",
    "source": "desidime",
    "image": "",
    "timestamp": "2026-04-18T05:15:41.148121+00:00"
  },
  {
    "text": "Hitachi 1.5 Ton 3 Star, New Star rated, Inverter Split AC @29654\n\nPay Using 6M No Cost EMI\n\n🔗 https://tinyurl.com/27p8a2dz\n\n🛒 Deals by @hugediscountshop",
    "url": "https://tinyurl.com/27p8a2dz",
    "product_url": "https://www.amazon.in/dp/B0GP71KXP5?th=1&ck&tag=lootdealska02-21",
    "source": "Loot_Deals_Xpress",
    "image": "",
    "timestamp": "2026-04-18T05:10:32.830740+00:00"
  },
  {
    "text": "Boat Nirvana Space, 360 Spatial Audio Earbuds Wireless @ ₹1,899 \n\n🔗https://www.amazon.in/boAt-Nirvana-Space-Cancellation-Bluetooth/dp/B0DDP7F317?th=1&tag=lootdealska02-21\n\n❌Regular price @ ₹2,009\n\n🔗 https://tinyurl.com/26hn2vnd\n\n🛒 Deals by @hugediscountshop",
    "url": "https://tinyurl.com/26hn2vnd",
    "product_url": "ttps://www.amazon.in/boAt-Nirvana-Space-Cancellation-Bluetooth/dp/B0DDP7F317?th=1&tag=lootdealska02-21\n",
    "source": "Loot_Deals_Xpress",
    "image": "",
    "timestamp": "2026-04-18T05:00:48.474559+00:00"
  },
  {
    "text": "Hitachi 1.5 Ton 3 Star, New Star rated, Inverter Split AC @ ₹30,999\n\n🔗https://www.amazon.in/dp/B0GP71KXP5?th=1&tag=lootdealska02-21\n\n❌Regular price @ ₹34,999\n\n💡Flat ₹4,000 off with SBI EMI\n\n🔗 https://tinyurl.com/27p8a2dz\n\n🛒 Deals by @hugediscountshop",
    "url": "https://tinyurl.com/27p8a2dz",
    "product_url": "ttps://www.amazon.in/dp/B0GP71KXP5?th=1&tag=lootdealska02-21\n",
    "source": "Loot_Deals_Xpress",
    "image": "",
    "timestamp": "2026-04-18T05:00:39.741395+00:00"
  },
  {
    "text": "70% off on - Myntra : Upto 70% Off On Adidas Shoes. - Rs. 2099\n\n🔗 https://tinyurl.com/2czgadmo\n\n🛒 Deals by @hugediscountshop",
    "url": "https://tinyurl.com/2czgadmo",
    "product_url": "https://www.myntra.com/adidas-shoes?sort=discount&f=Gender%3Amen%2Cmen%20women&rawQuery=adidas%20shoes&utm_source=dms_trafficaffiliates&utm_medium=dms_cuelinks_rev&utm_campaign=dms_trafficaffiliates_cuelinks_rev_20260418cldtg6fl3anq",
    "source": "desidimehot",
    "image": "",
    "timestamp": "2026-04-18T04:55:36.773798+00:00"
  },
  {
    "text": "70% off on - Myntra : Upto 70% Off On Adidas Shoes. - Rs. 2099\n\n🔗 https://tinyurl.com/29ffaupb\n\n🛒 Deals by @hugediscountshop",
    "url": "https://tinyurl.com/29ffaupb",
    "product_url": "https://www.myntra.com/adidas-shoes?sort=discount&f=Gender%3Amen%2Cmen%20women&rawQuery=adidas%20shoes&utm_source=dms_trafficaffiliates&utm_medium=dms_cuelinks_rev&utm_campaign=dms_trafficaffiliates_cuelinks_rev_20260418clybfgp8yjo4",
    "source": "desidime",
    "image": "",
    "timestamp": "2026-04-18T04:55:30.063219+00:00"
  },
  {
    "text": "Profusion Cosmetics 5 Shade Eye Shadow Palette - Terrific Tulip (4.55 g) for ₹111\n\n🔗 https://tinyurl.com/2ct34xw3\n\n🛒 Deals by @hugediscountshop",
    "url": "https://tinyurl.com/2ct34xw3",
    "product_url": "https://www.amazon.in/dp/B09X75SRL3?tag=megadealind-21",
    "source": "megadealind",
    "image": "",
    "timestamp": "2026-04-18T04:50:32.758373+00:00"
  },
  {
    "text": "Grab faast 🔥\n\n569₹\n\nOther colour costs more 🔥\n\n🔗 https://tinyurl.com/2ceguzdc\n\n🛒 Deals by @hugediscountshop",
    "url": "https://tinyurl.com/2ceguzdc",
    "product_url": "https://www.amazon.in/dp/B0DK9WVY8C?ck&tag=lootdealska02-21",
    "source": "Loot_Deals_Xpress",
    "image": "",
    "timestamp": "2026-04-18T04:45:30.846674+00:00"
  },
  {
    "text": "Buy max @ 249\n\n🔗 https://tinyurl.com/275mwp6z\n\n🛒 Deals by @hugediscountshop",
    "url": "https://tinyurl.com/275mwp6z",
    "product_url": "https://www.amazon.in/dp/B0G2LLRV4B?tag=lootdealska02-21",
    "source": "Loot_Deals_Xpress",
    "image": "",
    "timestamp": "2026-04-18T04:35:23.270543+00:00"
  },
  {
    "text": "🔥🔥Whirlpool 1.5 Ton 3 Star, Magicool Inverter Split AC\n\n🎁 Deal Price : ₹26,490\n\n💥 Bank Offer : ₹2,750 Off On AXIS, SBI Credit Cards EMI Txn\n\n🔗 https://tinyurl.com/24s7cw3t\n\n🛒 Deals by @hugediscountshop",
    "url": "https://tinyurl.com/24s7cw3t",
    "product_url": "https://www.amazon.in/dp/B0DSJ9FQLD?ck&tag=lootdealska02-21",
    "source": "Loot_Deals_Xpress",
    "image": "",
    "timestamp": "2026-04-18T04:30:36.802123+00:00"
  },
  {
    "text": "Apply ₹395 Coupon 🔥🔥\n\nHavells Capture 500W Mixer Grinder 3 Stainless Steel Jars @1840\n\n🔗 https://tinyurl.com/2douwvgy\n\n🛒 Deals by @hugediscountshop",
    "url": "https://tinyurl.com/2douwvgy",
    "product_url": "https://www.amazon.in/dp/B0D7VF87F4?th=1&ck&tag=lootdealska02-21",
    "source": "Loot_Deals_Xpress",
    "image": "",
    "timestamp": "2026-04-18T04:25:36.233181+00:00"
  },
  {
    "text": "Grab Deal 🔥\n\nMilton Artis Mixer Grinder, 3 Jar, 800 W ED (21000 RPM) at 2695/-\n\n🔗 https://tinyurl.com/26alc9cd\n\n🛒 Deals by @hugediscountshop",
    "url": "https://tinyurl.com/26alc9cd",
    "product_url": "https://www.amazon.in/dp/B0FD42TPGW?psc=1&ck&tag=lootdealska02-21",
    "source": "Loot_Deals_Xpress",
    "image": "",
    "timestamp": "2026-04-18T04:20:35.699122+00:00"
  },
  {
    "text": "🔥LOOT: Longway Royal Plus OTG 12 Ltr Oven Toaster Griller @1799\n\n🔗 https://tinyurl.com/28qgpauw\n\n🛒 Deals by @hugediscountshop",
    "url": "https://tinyurl.com/28qgpauw",
    "product_url": "https://www.amazon.in/Multiple-Temperature-Grilling-Toasting-warranty/dp/B0GTQ56Y1K?dib=eyJ2IjoiMSJ9.-6_CZv8fK8CRC6CSA2Te3mkhqu7nhuYcvpqibnLgTCiZmpwZ602X6Tp9Xhld7v3I3Z0juKox_96GczHNmpURj_dbozPhE9irKBqmdEUzE1GXMt_QYZXqO2MJJwpSCc-NTsRaAd4xm8R5u25ALpTw6w.fYDZG7HjtVd5jnt7hBEh_nO4PerDGkyrpBNEPYUyQrM&dib_tag=se&qid=1776485031&refinements=p_85%3A10440599031%2Cp_6%3AA3K8GDUW67973J%7CAXOGFIT0PZZ7G&rps=1&s=appliances&sr=1-721&xpid=bznu2_1anvwth&tag=lootdealska02-21&",
    "source": "Loot_Deals_Xpress",
    "image": "",
    "timestamp": "2026-04-18T04:15:48.325461+00:00"
  },
  {
    "text": "Longway Royal Plus OTG 12 Ltr Oven Toaster Griller @ 1799\n\n🔗 https://tinyurl.com/28qgpauw\n\n🛒 Deals by @hugediscountshop",
    "url": "https://tinyurl.com/28qgpauw",
    "product_url": "https://www.amazon.in/dp/B0GTQ56Y1K?ck&tag=lootdealska02-21",
    "source": "Loot_Deals_Xpress",
    "image": "",
    "timestamp": "2026-04-18T04:15:39.499893+00:00"
  },
  {
    "text": "🔥  Fridge Storage Box - 4Pcs at ₹99\n\n2-in-1 Veges & Fruit Peeler at ₹53\n\n🔗 https://tinyurl.com/2b4lgong\n\n🛒 Deals by @hugediscountshop",
    "url": "https://tinyurl.com/2b4lgong",
    "product_url": "https://www.amazon.in/dp/B0FVW8X8TK?social_share=cm_sw_r_apan_dp_V875PNCGWYY1P41ZDTGX&th=1&tag=lootdealska02-21",
    "source": "Loot_Deals_Xpress",
    "image": "",
    "timestamp": "2026-04-18T04:15:31.066235+00:00"
  },
  {
    "text": "Havells 80 L Desert Air Cooler for ₹7216 (Effectively)\n\nApply ₹1979 off with SBI Credit Card EMi.\n\n🔗 https://tinyurl.com/232v2cgh\n\n🛒 Deals by @hugediscountshop",
    "url": "https://tinyurl.com/232v2cgh",
    "product_url": "https://www.amazon.in/dp/B0DQKRHMHK?ck&tag=lootdealska02-21",
    "source": "Loot_Deals_Xpress",
    "image": "",
    "timestamp": "2026-04-18T04:10:48.453982+00:00"
  },
  {
    "text": "🔥Action | Athleo | RUNNER-119 Shoes @699\n\nPrice May Vary...\n\n🔗 https://tinyurl.com/29c4nopz\n\n🛒 Deals by @hugediscountshop",
    "url": "https://tinyurl.com/29c4nopz",
    "product_url": "https://www.amazon.in/dp/B0G1Z1XLT2?smid=A1WYWER0W24N8S&th=1&psc=1&tag=lootdealska02-21",
    "source": "Loot_Deals_Xpress",
    "image": "",
    "timestamp": "2026-04-18T04:10:37.901476+00:00"
  },
  {
    "text": "Xiaomi (43 inch) FX Pro QLED Ultra Smart Fire TV @ 25,999\n\n🔗 https://tinyurl.com/25d4soub\n\n🛒 Deals by @hugediscountshop",
    "url": "https://tinyurl.com/25d4soub",
    "product_url": "https://www.amazon.in/dp/B0F3JKY28G?th=1&ck&tag=lootdealska02-21",
    "source": "Loot_Deals_Xpress",
    "image": "",
    "timestamp": "2026-04-18T04:05:30.237489+00:00"
  },
  {
    "text": "70% Off : Lakme Hyaluronic Dewy Gel Creme @254\n\n🔗 https://tinyurl.com/27b36gzm\n\n🛒 Deals by @hugediscountshop",
    "url": "https://tinyurl.com/27b36gzm",
    "product_url": "https://www.amazon.in/dp/B07YVHVCZ3?tag=Rickeykaran77-21",
    "source": "amazinglootsdealsoffers",
    "image": "",
    "timestamp": "2026-04-18T04:01:09.959431+00:00"
  },
  {
    "text": "56% Off : Revlon Everyday Matte Liquid Lipstick @310\n\n🔗 https://tinyurl.com/2b8gbx6v\n\n🛒 Deals by @hugediscountshop",
    "url": "https://tinyurl.com/2b8gbx6v",
    "product_url": "https://www.amazon.in/dp/B0CWD5F43T?tag=Rickeykaran77-21",
    "source": "amazinglootsdealsoffers",
    "image": "",
    "timestamp": "2026-04-18T04:01:02.448524+00:00"
  },
  {
    "text": "Apply 10% Off coupon\n\n50% Off : Huggies Diapers L, (64 count, Pack Of 4) @2249\n\n🔗 https://tinyurl.com/2d4yy4ws\n\n🛒 Deals by @hugediscountshop",
    "url": "https://tinyurl.com/2d4yy4ws",
    "product_url": "https://www.amazon.in/dp/B0GS528BBH?tag=Rickeykaran77-21",
    "source": "amazinglootsdealsoffers",
    "image": "",
    "timestamp": "2026-04-18T04:00:54.276653+00:00"
  },
  {
    "text": "Apply 3% Off Coupon\n\n67% Off : Fiama Body Wash Shower Gel 900 ml @160\n\n🔗 https://tinyurl.com/2d2z63kl\n\n🛒 Deals by @hugediscountshop",
    "url": "https://tinyurl.com/2d2z63kl",
    "product_url": "https://www.amazon.in/dp/B098LR2L3K?tag=Rickeykaran77-21",
    "source": "amazinglootsdealsoffers",
    "image": "",
    "timestamp": "2026-04-18T04:00:47.520772+00:00"
  },
  {
    "text": "50% Off : POND'S Hydra Light Serum @300\n\n🔗 https://tinyurl.com/2d6zn4g3\n\n🛒 Deals by @hugediscountshop",
    "url": "https://tinyurl.com/2d6zn4g3",
    "product_url": "https://www.amazon.in/dp/B0CHW24T48?tag=Rickeykaran77-21",
    "source": "amazinglootsdealsoffers",
    "image": "",
    "timestamp": "2026-04-18T04:00:43.751000+00:00"
  },
  {
    "text": "53% Off : Colgate MaxFresh Toothpaste, 600g, 150g X 4 @287\n\n🔗 https://tinyurl.com/2b5vykfx\n\n🛒 Deals by @hugediscountshop",
    "url": "https://tinyurl.com/2b5vykfx",
    "product_url": "https://www.amazon.in/dp/B07JFW4CY4?tag=Rickeykaran77-21",
    "source": "amazinglootsdealsoffers",
    "image": "",
    "timestamp": "2026-04-18T04:00:36.424093+00:00"
  },
  {
    "text": "Olay 7in1 Ultra-light Gel Moisturizer @327\n\n🔗 https://tinyurl.com/268hh5wu\n\n🛒 Deals by @hugediscountshop",
    "url": "https://tinyurl.com/268hh5wu",
    "product_url": "https://www.amazon.in/dp/B0FH23CTP5?psc=1&th=1&ck&tag=lootdealska02-21",
    "source": "Loot_Deals_Xpress",
    "image": "",
    "timestamp": "2026-04-18T03:55:25.941631+00:00"
  },
  {
    "text": "MILTON Stainless Steel Casserole Set Of 3 at 532.\n\n🔗 https://tinyurl.com/29gsjnjy\n\n🛒 Deals by @hugediscountshop",
    "url": "https://tinyurl.com/29gsjnjy",
    "product_url": "https://www.amazon.in/dp/B0BX91Z8KX?ck&tag=lootdealska02-21",
    "source": "Loot_Deals_Xpress",
    "image": "",
    "timestamp": "2026-04-18T03:35:33.201742+00:00"
  },
  {
    "text": "50% off on - Duracell at 50% discount  - Rs. 110\n\n🔗 https://tinyurl.com/2c3leq7w\n\n🛒 Deals by @hugediscountshop",
    "url": "https://tinyurl.com/2c3leq7w",
    "product_url": "https://www.jiomart.com/search?q=Duracell",
    "source": "desidime",
    "image": "",
    "timestamp": "2026-04-18T03:25:24.958513+00:00"
  },
  {
    "text": "Apply 3% Off Coupon\n\n67% Off : Fiama Body Wash Shower Gel 900 ml @160\n\n🔗 https://tinyurl.com/2d2z63kl\n\n🛒 Deals by @hugediscountshop",
    "url": "https://tinyurl.com/2d2z63kl",
    "product_url": "https://www.amazon.in/dp/B098LR2L3K?psc=1&th=1&ck&tag=lootdealska02-21",
    "source": "Loot_Deals_Xpress",
    "image": "",
    "timestamp": "2026-04-18T03:15:29.082749+00:00"
  },
  {
    "text": "Apply 3% off Coupon\n\n67% off : Fiama Body Wash Shower Gel 900ml @ 160\n\n🔗 https://tinyurl.com/2d2z63kl\n\n🛒 Deals by @hugediscountshop",
    "url": "https://tinyurl.com/2d2z63kl",
    "product_url": "https://www.amazon.in/dp/B098LR2L3K?psc=1&th=1&tag=megadealind-21",
    "source": "megadealind",
    "image": "",
    "timestamp": "2026-04-18T03:10:46.341678+00:00"
  },
  {
    "text": "Grab faast 🔥\n\nPuma Men’s Running Shoes @919\n\nOther colour costs more 🔥\n\n🔗 https://tinyurl.com/2dpk9sum\n\n🛒 Deals by @hugediscountshop",
    "url": "https://tinyurl.com/2dpk9sum",
    "product_url": "https://www.amazon.in/dp/B07V2BSQFN?psc=1&th=1&ck&tag=lootdealska02-21",
    "source": "Loot_Deals_Xpress",
    "image": "",
    "timestamp": "2026-04-18T03:10:36.880208+00:00"
  },
  {
    "text": "Apply 10% off coupon\n\n50% off : Huggies Diapers L, (64 count, Pack of 4) @2249\n\n🔗 https://tinyurl.com/2d4yy4ws\n\n🛒 Deals by @hugediscountshop",
    "url": "https://tinyurl.com/2d4yy4ws",
    "product_url": "https://www.amazon.in/dp/B0GS528BBH?psc=1&th=1&ck&tag=lootdealska02-21",
    "source": "Loot_Deals_Xpress",
    "image": "",
    "timestamp": "2026-04-18T03:00:41.946609+00:00"
  },
  {
    "text": "Colgate MaxFresh Toothpaste 600g 150g X 4 @287\n\nMin. Buy 2\n\n🔗 https://tinyurl.com/2b5vykfx\n\n🛒 Deals by @hugediscountshop",
    "url": "https://tinyurl.com/2b5vykfx",
    "product_url": "https://www.amazon.in/dp/B07JFW4CY4?psc=1&th=1&ck&tag=lootdealska02-21",
    "source": "Loot_Deals_Xpress",
    "image": "",
    "timestamp": "2026-04-18T02:55:31.447010+00:00"
  },
  {
    "text": "Cello Opalware Floral Dinner Set, 19Pcs, White @904\n\n🔗 https://tinyurl.com/239fexcu\n\n🛒 Deals by @hugediscountshop",
    "url": "https://tinyurl.com/239fexcu",
    "product_url": "https://www.amazon.in/dp/B08XB9XYHD?psc=1&th=1&smid=AXOGFIT0PZZ7G&ck&tag=lootdealska02-21",
    "source": "Loot_Deals_Xpress",
    "image": "",
    "timestamp": "2026-04-18T02:45:38.572256+00:00"
  },
  {
    "text": "Aristocrat Set of 2 Luggage at ₹2,849.\n\n🔗 https://tinyurl.com/2bvyvvgq\n\n🛒 Deals by @hugediscountshop",
    "url": "https://tinyurl.com/2bvyvvgq",
    "product_url": "https://www.amazon.in/dp/B0C5DM79R9?th=1&ck&tag=lootdealska02-21",
    "source": "Loot_Deals_Xpress",
    "image": "",
    "timestamp": "2026-04-18T02:35:41.813596+00:00"
  },
  {
    "text": "SS Professional Jacket for Men's at 605.\n\n🔗 https://tinyurl.com/22d2sak8\n\n🛒 Deals by @hugediscountshop",
    "url": "https://tinyurl.com/22d2sak8",
    "product_url": "https://www.amazon.in/dp/B0CQ4Y6YRN?psc=1&ck&tag=lootdealska02-21",
    "source": "Loot_Deals_Xpress",
    "image": "",
    "timestamp": "2026-04-18T02:05:29.942789+00:00"
  },
  {
    "text": "Metal die cast 1👨7 - Orange at Rs.213.\nApply 3% coupon.\n\n🔗 https://tinyurl.com/23ws8o6e\n\n🛒 Deals by @hugediscountshop",
    "url": "https://tinyurl.com/23ws8o6e",
    "product_url": "https://www.amazon.in/dp/B0FZBX8KDR?aod=1&ck&tag=lootdealska02-21",
    "source": "Loot_Deals_Xpress",
    "image": "",
    "timestamp": "2026-04-18T01:55:34.709538+00:00"
  },
  {
    "text": "Grab🔥\n\nJACQUELINE DE YONG Women's Acrylic Blend Casual Sweater for ₹338\n\nOther sizes except xs costs 2k+\n\n🔗 https://tinyurl.com/27ucladm\n\n🛒 Deals by @hugediscountshop",
    "url": "https://tinyurl.com/27ucladm",
    "product_url": "https://www.amazon.in/dp/B0DJ2GVM72?psc=1&th=1&ck&tag=lootdealska02-21",
    "source": "Loot_Deals_Xpress",
    "image": "",
    "timestamp": "2026-04-18T01:50:33.262247+00:00"
  },
  {
    "text": "Get 10% Cashback Upto ₹150 On Bags & Luggage Order\n\nMin. Order Value ₹300\n\n🔗 https://tinyurl.com/2ap6qrqr\n\n🛒 Deals by @hugediscountshop",
    "url": "https://tinyurl.com/2ap6qrqr",
    "product_url": "https://www.amazon.in/h/rewards/dp/amzn1.rewards.rewardAd.YN2G7DWJ6JABC?rdpf=en&ck&tag=lootdealska02-21",
    "source": "Loot_Deals_Xpress",
    "image": "",
    "timestamp": "2026-04-18T01:15:36.165973+00:00"
  },
  {
    "text": "Grab 🔥\n\nMILTON Stainless Steel Casserole Set Of 3 @532.\n\nOther colour costs more 🔥\n\n🔗 https://tinyurl.com/29gsjnjy\n\n🛒 Deals by @hugediscountshop",
    "url": "https://tinyurl.com/29gsjnjy",
    "product_url": "https://www.amazon.in/dp/B0BX91Z8KX?ck&tag=lootdealska02-21",
    "source": "Loot_Deals_Xpress",
    "image": "",
    "timestamp": "2026-04-18T01:05:28.129281+00:00"
  },
  {
    "text": "Havells 1200mm Crista BLDC Motor Ceiling Fan with RF Remote and 100% Copper. for ₹5,800.\n\n• Apply ₹2500 Coupon on page.\n• ₹750 Off on HDFC Credit Card EMI Txn\n\nHavells 1320mm Florette Ceiling Fan with Remote Control for ₹7,641.\n\n• Apply ₹3000 Coupon on page.\n• ₹849 Off on SBI Credit Card EMI Txn.\n\nHavells 1200mm Momenta Underlight BLDC Ceiling Fan with Remote Control. for ₹8,999.\n\n• Apply ₹5000 Coupon on page.\n• ₹999 Off on SBI Credit Card EMI Txn.\n\n🔗 https://tinyurl.com/29xdq7bh\n\n🛒 Deals by @hugediscountshop",
    "url": "https://tinyurl.com/29xdq7bh",
    "product_url": "https://www.amazon.in/dp/B0C8B6MH6S?psc=1&th=1&ck&tag=lootdealska02-21",
    "source": "Loot_Deals_Xpress",
    "image": "",
    "timestamp": "2026-04-18T00:30:49.389436+00:00"
  },
  {
    "text": "Safari 2-piece 360° wheeling trolley bags with hard case polypropylene. for ₹3,501.\n\n• Apply 3% Coupon on page.\n\n🔗 https://tinyurl.com/297cmz2d\n\n🛒 Deals by @hugediscountshop",
    "url": "https://tinyurl.com/297cmz2d",
    "product_url": "https://www.amazon.in/dp/B097BFTPVH?psc=1&th=1&ck&tag=lootdealska02-21",
    "source": "Loot_Deals_Xpress",
    "image": "",
    "timestamp": "2026-04-18T00:30:41.386665+00:00"
  },
  {
    "text": "53% off on - Tata Sampann Hing 100g - Rs. 129\n\n🔗 https://tinyurl.com/24hob9hy\n\n🛒 Deals by @hugediscountshop",
    "url": "https://tinyurl.com/24hob9hy",
    "product_url": "https://www.jiomart.com/p/groceries/tata-sampann-hing-100g/609923498",
    "source": "desidime",
    "image": "",
    "timestamp": "2026-04-17T19:35:39.958783+00:00"
  },
  {
    "text": "🔥🔥\n157₹\n\nLakmé Forever Matte Liquid Lip Colour, Nude Myth, 5.6 ml\n\n🔗 https://tinyurl.com/2d2hpnr8\n\n🛒 Deals by @hugediscountshop",
    "url": "https://tinyurl.com/2d2hpnr8",
    "product_url": "https://www.amazon.in/dp/B0828W1Z5M?th=1&ck&tag=lootdealska02-21",
    "source": "Loot_Deals_Xpress",
    "image": "",
    "timestamp": "2026-04-17T19:31:03.262158+00:00"
  },
  {
    "text": "🔥🔥\n280₹\n\nJam & Honey- Peppa Pig Purse Beauty Set | Toy for Kids Age 3+ Years\n\n🔗 https://tinyurl.com/255f8jvw\n\n🛒 Deals by @hugediscountshop",
    "url": "https://tinyurl.com/255f8jvw",
    "product_url": "https://www.amazon.in/dp/B0FR4QYBDN?th=1&aod=1&ck&tag=lootdealska02-21",
    "source": "Loot_Deals_Xpress",
    "image": "",
    "timestamp": "2026-04-17T19:30:53.975431+00:00"
  },
  {
    "text": "🔥🔥\n548₹\n\nHavells Utility DB SPN SD QVE RG 4W Metal Single Door Distribution Board (Grey)\n\n🔗 https://tinyurl.com/2ctqzjzp\n\n🛒 Deals by @hugediscountshop",
    "url": "https://tinyurl.com/2ctqzjzp",
    "product_url": "https://www.amazon.in/dp/B07BH5K49X?ck&tag=lootdealska02-21",
    "source": "Loot_Deals_Xpress",
    "image": "",
    "timestamp": "2026-04-17T19:30:44.013842+00:00"
  },
  {
    "text": "Amazon | Haier 1.5 Ton 4 Star AI Climate Control Smart Split AC @30740\n\nApply 2000 Off Coupon + 2750 Off With SBI Credit Card\n\n🔗 https://tinyurl.com/23zha88j\n\n🛒 Deals by @hugediscountshop",
    "url": "https://tinyurl.com/23zha88j",
    "product_url": "https://www.amazon.in/dp/B0DW4B3Y9Q?ck&tag=lootdealska02-21",
    "source": "Loot_Deals_Xpress",
    "image": "",
    "timestamp": "2026-04-17T19:20:27.545573+00:00"
  },
  {
    "text": "Flipkart | Lenovo LOQ AMD Ryzen 7 Octa Core Gaming Laptop ,240\n\n11,750₹ off with HDFC Card\n\n🔗 https://tinyurl.com/2cecs3om\n\n🛒 Deals by @hugediscountshop",
    "url": "https://tinyurl.com/2cecs3om",
    "product_url": "https://linkredirect.in/visitretailer/2276?id=791399&shareid=TKgAeKo&dl=https%3A%2F%2Fwww.flipkart.com%2Fa%2Fp%2Fitm9c22c819b1392%3Fpid%3DCOMHKYFSFB9NZDUS%26lid%3DLSTCOMHKYFSFB9NZDUS4GVWGV%26marketplace%3DFLIPKART&source=Default",
    "source": "megadealind",
    "image": "",
    "timestamp": "2026-04-17T19:15:48.168987+00:00"
  },
  {
    "text": ".\n\nFiama Body Wash, 895 ml 🔥\n160₹\n Coupon\n\n🔗 https://tinyurl.com/2d2z63kl\n\n🛒 Deals by @hugediscountshop",
    "url": "https://tinyurl.com/2d2z63kl",
    "product_url": "https://www.amazon.in/dp/B098LR2L3K?psc=1&th=1&ck&tag=lootdealska02-21",
    "source": "Loot_Deals_Xpress",
    "image": "",
    "timestamp": "2026-04-17T19:15:34.095692+00:00"
  },
  {
    "text": "Get 10% Cashback Upto ₹150 On Min. ₹300 Bags & Luggage Order.\n\n🔗 https://tinyurl.com/2ap6qrqr\n\n🛒 Deals by @hugediscountshop",
    "url": "https://tinyurl.com/2ap6qrqr",
    "product_url": "https://www.amazon.in/h/rewards/dp/amzn1.rewards.rewardAd.YN2G7DWJ6JABC?rdpf=en&ck&tag=lootdealska02-21",
    "source": "Loot_Deals_Xpress",
    "image": "",
    "timestamp": "2026-04-17T19:10:32.256186+00:00"
  },
  {
    "text": "Hitachi 1.5 Ton 3 Star, New Star rated, Inverter Split AC @27,999\n\n7000 Off With SBI Credit Card\n\n🔗 https://tinyurl.com/27p8a2dz\n\n🛒 Deals by @hugediscountshop",
    "url": "https://tinyurl.com/27p8a2dz",
    "product_url": "https://www.amazon.in/dp/B0GP71KXP5?tag=Rickeykaran77-21",
    "source": "amazinglootsdealsoffers",
    "image": "",
    "timestamp": "2026-04-17T19:10:25.036749+00:00"
  },
  {
    "text": "🔥🔥\n516₹\nCoupon \n\nMILTON Stainless Steel Casserole Set Of 3\n\n🔗 https://tinyurl.com/29gsjnjy\n\n🛒 Deals by @hugediscountshop",
    "url": "https://tinyurl.com/29gsjnjy",
    "product_url": "https://www.amazon.in/dp/B0BX91Z8KX?ck&tag=lootdealska02-21",
    "source": "Loot_Deals_Xpress",
    "image": "",
    "timestamp": "2026-04-17T19:05:43.338393+00:00"
  },
  {
    "text": "Flipkart | 68% Off - Yardley Deo 200Ml Eack , ( Set Of 3) At Rs.307\n\n🔗 https://tinyurl.com/25dtql5g\n\n🛒 Deals by @hugediscountshop",
    "url": "https://tinyurl.com/25dtql5g",
    "product_url": "https://linkredirect.in/visitretailer/2276?id=791399&shareid=d9N9w97&dl=https%3A%2F%2Fwww.flipkart.com%2Fyardley-london-english-lavender-refreshing-body-spray-200ml-deodorant-women%2Fp%2Fitmdcf5b2fe12d45%3Fpid%3DDEOH3AHGNGN5FCNE&source=Default",
    "source": "megadealind",
    "image": "",
    "timestamp": "2026-04-17T18:56:00.442409+00:00"
  },
  {
    "text": "10% off on - Amazon: Get 10% upto ₹200 Min ₹2000 of Personal Care Appliances order - Rs. 1800\n\n🔗 https://tinyurl.com/26u6nfr8\n\n🛒 Deals by @hugediscountshop",
    "url": "https://tinyurl.com/26u6nfr8",
    "product_url": "https://www.amazon.in/h/rewards/dp/amzn1.rewards.rewardAd.J2HZVU7ZPPNJG?rdpf=en&tag=desidimetelegram-21&ascsubtag=20260418clljzwxf59lr",
    "source": "desidime",
    "image": "",
    "timestamp": "2026-04-17T18:55:47.769766+00:00"
  },
  {
    "text": "Amazon Grab : Whirlpool 1.5 Ton 3 Star 2026 Model @26839\n\nApply 250 Coupon + 3250 off via HDFC CC\n\n🔗 https://tinyurl.com/247uc7cb\n\n🛒 Deals by @hugediscountshop",
    "url": "https://tinyurl.com/247uc7cb",
    "product_url": "https://www.amazon.in/dp/B0GHQVN35Z?psc=1&ck&tag=lootdealska02-21",
    "source": "Loot_Deals_Xpress",
    "image": "",
    "timestamp": "2026-04-17T18:55:39.280685+00:00"
  },
  {
    "text": "Amazon | Parachute Advansed Jasmine Coconut Hair Oil, 600ml @194\n\n🔗 https://tinyurl.com/29nj5haw\n\n🛒 Deals by @hugediscountshop",
    "url": "https://tinyurl.com/29nj5haw",
    "product_url": "https://www.amazon.in/dp/B0FY67CG6W?psc=1&th=1&ck&tag=lootdealska02-21",
    "source": "Loot_Deals_Xpress",
    "image": "",
    "timestamp": "2026-04-17T18:55:32.766480+00:00"
  },
  {
    "text": "Amazon | Amazonbasics Wireless Mouse 🔥 \n170₹\n\n🔗 https://tinyurl.com/246xyb3q\n\n🛒 Deals by @hugediscountshop",
    "url": "https://tinyurl.com/246xyb3q",
    "product_url": "https://www.amazon.in/dp/B0DWSTJG8G?psc=1&th=1&tag=megadealind-21",
    "source": "megadealind",
    "image": "",
    "timestamp": "2026-04-17T18:46:27.458656+00:00"
  },
  {
    "text": "Whirlpool 1.5 Ton 3 Star 2026 Model @ 26839\n\n-   Apply 250 Coupon\n-   3250 off via HDFC CC\n\n🔗 https://tinyurl.com/247uc7cb\n\n🛒 Deals by @hugediscountshop",
    "url": "https://tinyurl.com/247uc7cb",
    "product_url": "https://www.amazon.in/dp/B0GHQVN35Z?psc=1&tag=megadealind-21",
    "source": "megadealind",
    "image": "",
    "timestamp": "2026-04-17T18:46:23.076496+00:00"
  },
  {
    "text": "Amazon | SNITCH Men's T-Shirt 🔥\n499₹\n\n🔗 https://tinyurl.com/2cqgfzl7\n\n🛒 Deals by @hugediscountshop",
    "url": "https://tinyurl.com/2cqgfzl7",
    "product_url": "https://www.amazon.in/dp/B0G1ZT83TX?psc=1&th=1&aod=1&ck&tag=lootdealska02-21",
    "source": "Loot_Deals_Xpress",
    "image": "",
    "timestamp": "2026-04-17T18:46:13.096073+00:00"
  },
  {
    "text": "Amazon | Amazonbasics Wireless Mouse 🔥 \n170₹\n\n🔗 https://tinyurl.com/246xyb3q\n\n🛒 Deals by @hugediscountshop",
    "url": "https://tinyurl.com/246xyb3q",
    "product_url": "https://www.amazon.in/dp/B0DWSTJG8G?psc=1&th=1&ck&tag=lootdealska02-21",
    "source": "Loot_Deals_Xpress",
    "image": "",
    "timestamp": "2026-04-17T18:46:00.261676+00:00"
  },
  {
    "text": "🔥🔥\n194₹\nCoupon \n\nParachute Advansed Jasmine Coconut Hair Oil, 600ml\n\n🔗 https://tinyurl.com/29nj5haw\n\n🛒 Deals by @hugediscountshop",
    "url": "https://tinyurl.com/29nj5haw",
    "product_url": "https://www.amazon.in/dp/B0FY67CG6W?psc=1&th=1&ck&tag=lootdealska02-21",
    "source": "Loot_Deals_Xpress",
    "image": "",
    "timestamp": "2026-04-17T18:45:55.648801+00:00"
  },
  {
    "text": "Car Cover @377.\n\n🔗 https://tinyurl.com/2a9spqnq\n\n🛒 Deals by @hugediscountshop",
    "url": "https://tinyurl.com/2a9spqnq",
    "product_url": "https://www.amazon.in/dp/B09YMFPYH6?tag=Rickeykaran77-21",
    "source": "amazinglootsdealsoffers",
    "image": "",
    "timestamp": "2026-04-17T18:45:41.643048+00:00"
  },
  {
    "text": "56% Off : Parachute Advansed Jasmine Coconut Hair Oil, 600ml @199\n\n🔗 https://tinyurl.com/29nj5haw\n\n🛒 Deals by @hugediscountshop",
    "url": "https://tinyurl.com/29nj5haw",
    "product_url": "https://www.amazon.in/dp/B0FY67CG6W?tag=Rickeykaran77-21",
    "source": "amazinglootsdealsoffers",
    "image": "",
    "timestamp": "2026-04-17T18:45:35.523664+00:00"
  },
  {
    "text": "Get 12% Cashback Upto Rs.300 On Bags & Luggage Order\n\nMin. Order Value Rs.500\n\n🔗 https://tinyurl.com/2brzlu44\n\n🛒 Deals by @hugediscountshop",
    "url": "https://tinyurl.com/2brzlu44",
    "product_url": "https://www.amazon.in/h/rewards/dp/amzn1.rewards.rewardAd.DJTFB3HTWK63E?rdpf=en&%3Btag=dworth-21&tag=Rickeykaran77-21",
    "source": "amazinglootsdealsoffers",
    "image": "",
    "timestamp": "2026-04-17T18:45:29.489097+00:00"
  },
  {
    "text": "Get 10% Cashback Upto ₹150 On Bags & Luggage Order\n\nMin. Order Value ₹300\n\n🔗 https://tinyurl.com/2693xtqa\n\n🛒 Deals by @hugediscountshop",
    "url": "https://tinyurl.com/2693xtqa",
    "product_url": "https://www.amazon.in/h/rewards/dp/amzn1.rewards.rewardAd.YN2G7DWJ6JABC?rdpf=en&tag=megadealind-21",
    "source": "megadealind",
    "image": "",
    "timestamp": "2026-04-17T18:41:05.588770+00:00"
  },
  {
    "text": "Flipkart | 67% Off - Havells Air Cooler , 80L At Rs.8,999\n\nRegular Rs.13,364\n\n🔗 https://tinyurl.com/22xg8ehq\n\n🛒 Deals by @hugediscountshop",
    "url": "https://tinyurl.com/22xg8ehq",
    "product_url": "https://linkredirect.in/visitretailer/2276?id=791399&shareid=q6gJXeM&dl=https%3A%2F%2Fwww.flipkart.com%2FindiaXdesire-deals%2Fp%2Findia_fg_desire_deals%3Fpid%3DAICH7NW7YEK4MNXP%26lid%3DLSTAICH7NW7YEK4MNXPMLKDKZ%26marketplace%3DFLIPKART&source=Default",
    "source": "megadealind",
    "image": "",
    "timestamp": "2026-04-17T18:40:59.583209+00:00"
  },
  {
    "text": "Amazon | SNITCH Men's T-Shirt 🔥\n499₹\n\n🔗 https://tinyurl.com/2cqgfzl7\n\n🛒 Deals by @hugediscountshop",
    "url": "https://tinyurl.com/2cqgfzl7",
    "product_url": "https://www.amazon.in/dp/B0G1ZT83TX?psc=1&th=1&aod=1&tag=megadealind-21",
    "source": "megadealind",
    "image": "",
    "timestamp": "2026-04-17T18:40:47.755467+00:00"
  },
  {
    "text": "Apply ₹51800 Coupon\n\nHome Centre Vegas Faux Marble Top 6-Seater Dining Set with Chairs - Beige\n\n🔗 https://tinyurl.com/2ykmv94s\n\n🛒 Deals by @hugediscountshop",
    "url": "https://tinyurl.com/2ykmv94s",
    "product_url": "https://www.amazon.in/dp/B0CYT8WV98?psc=1&th=1&tag=megadealind-21",
    "source": "megadealind",
    "image": "",
    "timestamp": "2026-04-17T18:36:26.846106+00:00"
  },
  {
    "text": "Get 10% Cashback Upto Rs.150 On Bags & Luggage Order\n\nMin. Order Value Rs.300\n\n🔗 https://tinyurl.com/2693xtqa\n\n🛒 Deals by @hugediscountshop",
    "url": "https://tinyurl.com/2693xtqa",
    "product_url": "https://www.amazon.in/h/rewards/dp/amzn1.rewards.rewardAd.YN2G7DWJ6JABC?rdpf=en&tag=megadealind-21",
    "source": "megadealind",
    "image": "",
    "timestamp": "2026-04-17T18:36:12.128443+00:00"
  },
  {
    "text": "Apply ₹51800 Coupon\n\nHome Centre Vegas Faux Marble Top 6-Seater Dining Set with Chairs - Beige @48195\n\n🔗 https://tinyurl.com/2ykmv94s\n\n🛒 Deals by @hugediscountshop",
    "url": "https://tinyurl.com/2ykmv94s",
    "product_url": "https://www.amazon.in/dp/B0CYT8WV98?psc=1&th=1&ck&tag=lootdealska02-21",
    "source": "Loot_Deals_Xpress",
    "image": "",
    "timestamp": "2026-04-17T18:35:59.352364+00:00"
  },
  {
    "text": "Get 10% Cashback Upto Rs.150 On Bags & Luggage Order\n\nMin. Order Value Rs.300\n\n🔗 https://tinyurl.com/2ap6qrqr\n\n🛒 Deals by @hugediscountshop",
    "url": "https://tinyurl.com/2ap6qrqr",
    "product_url": "https://www.amazon.in/h/rewards/dp/amzn1.rewards.rewardAd.YN2G7DWJ6JABC?rdpf=en&ck&tag=lootdealska02-21",
    "source": "Loot_Deals_Xpress",
    "image": "",
    "timestamp": "2026-04-17T18:35:50.017057+00:00"
  },
  {
    "text": "68% Off : Smart And Handsome Face Wash, 150ml @113.\n\n🔗 https://tinyurl.com/237jp7z4\n\n🛒 Deals by @hugediscountshop",
    "url": "https://tinyurl.com/237jp7z4",
    "product_url": "https://www.amazon.in/dp/B0B4GYZ4FR?tag=Rickeykaran77-21",
    "source": "amazinglootsdealsoffers",
    "image": "",
    "timestamp": "2026-04-17T18:35:45.280290+00:00"
  },
  {
    "text": "Whirlpool HD 1.5 Ton 3 Star Inverter Split Air Conditioner at ₹26,240.\n\nApply ₹250 Coupon on page.\n ₹3,750 Off on HDFC Credit Card EMI Txn.\n\nNon‑EMI Offer: ₹3,250 Off on HDFC Credit Card.\n\n🔗 https://tinyurl.com/247uc7cb\n\n🛒 Deals by @hugediscountshop",
    "url": "https://tinyurl.com/247uc7cb",
    "product_url": "https://www.amazon.in/dp/B0GHQVN35Z?tag=Rickeykaran77-21",
    "source": "amazinglootsdealsoffers",
    "image": "",
    "timestamp": "2026-04-17T18:35:33.107657+00:00"
  },
  {
    "text": "Get 10% Cashback Upto Rs.150 On Bags & Luggage Order\n\nMin. Order Value Rs.300\n\n🔗 https://tinyurl.com/2ygtgzzh\n\n🛒 Deals by @hugediscountshop",
    "url": "https://tinyurl.com/2ygtgzzh",
    "product_url": "https://www.amazon.in/h/rewards/dp/amzn1.rewards.rewardAd.YN2G7DWJ6JABC?rdpf=en&%3Btag=dworth-21&tag=Rickeykaran77-21",
    "source": "amazinglootsdealsoffers",
    "image": "",
    "timestamp": "2026-04-17T18:35:26.313982+00:00"
  },
  {
    "text": "Amazon | Office Chair @3783\n\n🔗 https://tinyurl.com/2cr2merb\n\n🛒 Deals by @hugediscountshop",
    "url": "https://tinyurl.com/2cr2merb",
    "product_url": "https://www.amazon.in/dp/B09XMHY37W?psc=1&th=1&smid=AXOGFIT0PZZ7G&ck&tag=lootdealska02-21",
    "source": "Loot_Deals_Xpress",
    "image": "",
    "timestamp": "2026-04-17T18:30:41.553399+00:00"
  },
  {
    "text": "Amazonbasics Wireless Mouse at 170.\n\n🔗 https://tinyurl.com/246xyb3q\n\n🛒 Deals by @hugediscountshop",
    "url": "https://tinyurl.com/246xyb3q",
    "product_url": "https://www.amazon.in/dp/B0DWSTJG8G?psc=1&th=1&tag=megadealind-21",
    "source": "megadealind",
    "image": "",
    "timestamp": "2026-04-17T18:20:38.859283+00:00"
  },
  {
    "text": ".\n\nAmazonbasics Wireless Mouse 🔥 \n170₹\n\n🔗 https://tinyurl.com/246xyb3q\n\n🛒 Deals by @hugediscountshop",
    "url": "https://tinyurl.com/246xyb3q",
    "product_url": "https://www.amazon.in/dp/B0DWSTJG8G?psc=1&th=1&ck&tag=lootdealska02-21",
    "source": "Loot_Deals_Xpress",
    "image": "",
    "timestamp": "2026-04-17T18:20:27.384668+00:00"
  },
  {
    "text": "Amazon | Longway Sage 500 Watt Juicer Mixer Grinder @1099\n\n🔗 https://tinyurl.com/2c5g79q8\n\n🛒 Deals by @hugediscountshop",
    "url": "https://tinyurl.com/2c5g79q8",
    "product_url": "https://www.amazon.in/dp/B0C24NDQK4?ck&tag=lootdealska02-21",
    "source": "Loot_Deals_Xpress",
    "image": "",
    "timestamp": "2026-04-17T18:15:58.017217+00:00"
  },
  {
    "text": "🔥🔥\n1,049₹\n\nLongway Sage 500 Watt Juicer Mixer Grinder\n\n🔗 https://tinyurl.com/2c5g79q8\n\n🛒 Deals by @hugediscountshop",
    "url": "https://tinyurl.com/2c5g79q8",
    "product_url": "https://www.amazon.in/dp/B0C24NDQK4?th=1&ck&tag=lootdealska02-21",
    "source": "Loot_Deals_Xpress",
    "image": "",
    "timestamp": "2026-04-17T18:15:42.855498+00:00"
  },
  {
    "text": ".\n\nOrient Electric Titan 100L Desert Air Cooler for Home 1 Year Warranty by Orient\n\n10,499₹\n\n🔗 https://tinyurl.com/24olbefq\n\n🛒 Deals by @hugediscountshop",
    "url": "https://tinyurl.com/24olbefq",
    "product_url": "https://www.amazon.in/dp/B0BVFW1NPD?ck&tag=lootdealska02-21",
    "source": "Loot_Deals_Xpress",
    "image": "",
    "timestamp": "2026-04-17T18:10:40.440601+00:00"
  },
  {
    "text": "Grab 💥 \n616₹\n\nTrunkit Adventure Series Water Resistance Trekking Hiking Travel Bag with Shoe Compartment Rucksack - 55 L\n\n🔗 https://tinyurl.com/2b9w4kdq\n\n🛒 Deals by @hugediscountshop",
    "url": "https://tinyurl.com/2b9w4kdq",
    "product_url": "https://www.amazon.in/dp/B08L6G2FSH?th=1&ck&tag=lootdealska02-21",
    "source": "Loot_Deals_Xpress",
    "image": "",
    "timestamp": "2026-04-17T18:10:34.854429+00:00"
  },
  {
    "text": ".\n\nPepe Jeans Men's Jeans 🔥 \n1,069₹\n\n🔗 https://tinyurl.com/2ckt994x\n\n🛒 Deals by @hugediscountshop",
    "url": "https://tinyurl.com/2ckt994x",
    "product_url": "https://www.amazon.in/dp/B0DHHCF9W1?psc=1&th=1&smid=A1WYWER0W24N8S&ck&tag=lootdealska02-21",
    "source": "Loot_Deals_Xpress",
    "image": "",
    "timestamp": "2026-04-17T18:05:46.494768+00:00"
  },
  {
    "text": "Amazon | HomeWiz Airtight Plastic Food Storage Containers Set | 4-Piece @199\n\n🔗 https://tinyurl.com/29sz29ju\n\n🛒 Deals by @hugediscountshop",
    "url": "https://tinyurl.com/29sz29ju",
    "product_url": "https://www.amazon.in/dp/B0FVW78JB2?psc=1&th=1&ck&tag=lootdealska02-21",
    "source": "Loot_Deals_Xpress",
    "image": "",
    "timestamp": "2026-04-17T18:05:37.132884+00:00"
  },
  {
    "text": "Pepe Jeans Men Jeans at ₹1069\n\n🔗 https://tinyurl.com/2ckt994x\n\n🛒 Deals by @hugediscountshop",
    "url": "https://tinyurl.com/2ckt994x",
    "product_url": "https://www.amazon.in/dp/B0DHHCF9W1?psc=1&th=1&tag=megadealind-21",
    "source": "megadealind",
    "image": "",
    "timestamp": "2026-04-17T18:01:15.830255+00:00"
  },
  {
    "text": ".\n\nAmazon Bazaar 💥\n50₹\n\n🔗 https://tinyurl.com/2ybt7h99\n\n🛒 Deals by @hugediscountshop",
    "url": "https://tinyurl.com/2ybt7h99",
    "product_url": "https://www.amazon.in/dp/B0FWBSWB89?psc=1&th=1&ck&tag=lootdealska02-21",
    "source": "Loot_Deals_Xpress",
    "image": "",
    "timestamp": "2026-04-17T18:00:40.063483+00:00"
  },
  {
    "text": ".\n\nWildHorn 31L Laptop Backpack 🔥\n599₹\n\n🔗 https://tinyurl.com/2cwkpk5y\n\n🛒 Deals by @hugediscountshop",
    "url": "https://tinyurl.com/2cwkpk5y",
    "product_url": "https://www.amazon.in/dp/B09YNYD6MX?smid=AXOGFIT0PZZ7G&ck&tag=lootdealska02-21",
    "source": "Loot_Deals_Xpress",
    "image": "",
    "timestamp": "2026-04-17T17:55:47.444227+00:00"
  },
  {
    "text": "🔥🔥\n2,035₹\n\nBergner BE Essentials Tripro Triply Outer Lid Pressure Cooker 2.9 Litres\n\n🔗 https://tinyurl.com/27q8hxz7\n\n🛒 Deals by @hugediscountshop",
    "url": "https://tinyurl.com/27q8hxz7",
    "product_url": "https://www.amazon.in/dp/B0DKFC28PQ?psc=1&th=1&smid=AXOGFIT0PZZ7G&ck&tag=lootdealska02-21",
    "source": "Loot_Deals_Xpress",
    "image": "",
    "timestamp": "2026-04-17T17:55:34.238350+00:00"
  },
  {
    "text": "🔥🔥\n1,673₹\n\nNIRLON Induction and Gas Stove Compatible Outer Lid Belly Triply Stainless Steel Pressure Cooker (2 Liters)\n\n🔗 https://tinyurl.com/26chyfyv\n\n🛒 Deals by @hugediscountshop",
    "url": "https://tinyurl.com/26chyfyv",
    "product_url": "https://www.amazon.in/dp/B0CM9N2GGF?th=1&smid=AXOGFIT0PZZ7G&ck&tag=lootdealska02-21",
    "source": "Loot_Deals_Xpress",
    "image": "",
    "timestamp": "2026-04-17T17:50:33.332695+00:00"
  },
  {
    "text": "🔥🔥\n213₹\n\nVaseline Daily Brightening Body Lotion with Niacinamide 400ml\n\n🔗 https://tinyurl.com/2bxveahw\n\n🛒 Deals by @hugediscountshop",
    "url": "https://tinyurl.com/2bxveahw",
    "product_url": "https://www.amazon.in/dp/B09ZL9QY3B?psc=1&th=1&ck&tag=lootdealska02-21",
    "source": "Loot_Deals_Xpress",
    "image": "",
    "timestamp": "2026-04-17T17:40:49.567844+00:00"
  },
  {
    "text": ".\n\nGrab 💥 \n4,791₹\nCoupon \n\nSafari 3-Piece Trolley Bag Set with 8-Wheels and Hard Case\n\n🔗 https://tinyurl.com/25mxo2p5\n\n🛒 Deals by @hugediscountshop",
    "url": "https://tinyurl.com/25mxo2p5",
    "product_url": "https://www.amazon.in/dp/B097BGSJX1?psc=1&th=1&ck&tag=lootdealska02-21",
    "source": "Loot_Deals_Xpress",
    "image": "",
    "timestamp": "2026-04-17T17:40:40.614189+00:00"
  },
  {
    "text": "🔥  Hair & Care Almond Hair Oil 500ml @ ₹69\n\nMin Buy - 2\n\n🔗 https://tinyurl.com/26wuv4a2\n\n🛒 Deals by @hugediscountshop",
    "url": "https://tinyurl.com/26wuv4a2",
    "product_url": "https://www.amazon.in/dp/B07S2SKYTH?smid=A15APWRK6P7LBV&psc=1&th=1&tag=lootdealska02-21",
    "source": "Loot_Deals_Xpress",
    "image": "",
    "timestamp": "2026-04-17T17:35:37.401193+00:00"
  },
  {
    "text": "67% Off : Fiama Body Wash 895 ml @165.\n\n🔗 https://tinyurl.com/2d2z63kl\n\n🛒 Deals by @hugediscountshop",
    "url": "https://tinyurl.com/2d2z63kl",
    "product_url": "https://www.amazon.in/dp/B098LR2L3K?tag=Rickeykaran77-21",
    "source": "amazinglootsdealsoffers",
    "image": "",
    "timestamp": "2026-04-17T17:35:23.441440+00:00"
  },
  {
    "text": "Flipkart GOLD - Extra 5% off Coupons for selected accounts \n\nUse Discounted GVs for more benefit and Lower Cost\n\n2g @ 30976  ( Cheapest)\n\n0.5Gm\n\n1Gm\n\n5Gm\n\nOther Brands - \n1gm 995\n\nMasterlink\n\n🔗 https://tinyurl.com/29a56nl9\n\n🛒 Deals by @hugediscountshop",
    "url": "https://tinyurl.com/29a56nl9",
    "product_url": "https://linkredirect.in/visitretailer/2276?id=791399&shareid=iHQQWv6&dl=https%3A%2F%2Fwww.flipkart.com%2Fflipkart%2Fp%2Fitem%3Fpid%3DCONH2N7KZFCDYJCZ%26lid%3DLSTCONH2N7KZFCDYJCZFK19P7%26marketplace%3DFLIPKART&source=Default",
    "source": "megadealind",
    "image": "",
    "timestamp": "2026-04-17T17:30:50.394071+00:00"
  },
  {
    "text": "Upto 50% Off on Jabra Evolve On-Ear Headset with Noise canceling mic\n\nApply Code : JABRA250 (Flat ₹250 Off)\n\n🔗 https://tinyurl.com/2768nedc\n\n🛒 Deals by @hugediscountshop",
    "url": "https://tinyurl.com/2768nedc",
    "product_url": "https://www.amazon.in/s?hidden-keywords=B0F1DGSZPZ%7CB0DX7D572Y&&ck&tag=lootdealska02-21&",
    "source": "Loot_Deals_Xpress",
    "image": "",
    "timestamp": "2026-04-17T17:25:36.047271+00:00"
  },
  {
    "text": "Ranveer Singh Outfit Recreate \n\nJacket @ ₹1812\nhttps://ajiio.in/tAgW7Z4\n\nTank top @ ₹189\n\nCargos @ ₹720\n\nSunglasses @ ₹139\n\nSneakers @ ₹553\n\n🔗 https://tinyurl.com/232vngjl\n\n🛒 Deals by @hugediscountshop",
    "url": "https://tinyurl.com/232vngjl",
    "product_url": "https://linkredirect.in/visitretailer/2276?id=791399&shareid=jH3zLpJ&dl=https%3A%2F%2Fwww.flipkart.com%2Fkelonbro-men-vest%2Fp%2Fitm960a37bd0319e%3Fpid%3DVESHA69GYHM3Z77J%26lid%3DLSTVESHA69GYHM3Z77JXIKPMB%26marketplace%3DFLIPKART&source=Default",
    "source": "megadealind",
    "image": "",
    "timestamp": "2026-04-17T17:20:39.529269+00:00"
  },
  {
    "text": ".\n\nSurf Excel Detergent Powder 7Kg 🔥\n673₹\n\n🔗 https://tinyurl.com/ytaj8keg\n\n🛒 Deals by @hugediscountshop",
    "url": "https://tinyurl.com/ytaj8keg",
    "product_url": "https://www.amazon.in/dp/B0D7GQNL6B?ck&tag=lootdealska02-21",
    "source": "Loot_Deals_Xpress",
    "image": "",
    "timestamp": "2026-04-17T17:15:29.867394+00:00"
  },
  {
    "text": "82% off on - Fruits and veggies up to 81 % off! (location specific 400075) - Rs. 6\n\n🔗 https://tinyurl.com/2dx92v8g\n\n🛒 Deals by @hugediscountshop",
    "url": "https://tinyurl.com/2dx92v8g",
    "product_url": "https://www.swiggy.com/stores/instamart/item/A4RKJ8JRVI?share=true",
    "source": "desidime",
    "image": "",
    "timestamp": "2026-04-17T17:05:46.057153+00:00"
  },
  {
    "text": "Grab 💥 \n649₹\n\nHavells Glydo 1000 watt Dry Iron With American Heritage Non Stick Sole Plate\n\n🔗 https://tinyurl.com/2762b2sr\n\n🛒 Deals by @hugediscountshop",
    "url": "https://tinyurl.com/2762b2sr",
    "product_url": "https://www.amazon.in/dp/B07LDPLSZC?th=1&ck&tag=lootdealska02-21",
    "source": "Loot_Deals_Xpress",
    "image": "",
    "timestamp": "2026-04-17T17:05:37.292936+00:00"
  },
  {
    "text": "Aspect (995) 1gm Gold @ 14482 using RBL Cards\n\n🔗 https://tinyurl.com/2cxnpn9c\n\n🛒 Deals by @hugediscountshop",
    "url": "https://tinyurl.com/2cxnpn9c",
    "product_url": "https://www.ajio.com/?utm_source=trafficback&utm_medium=affiliate",
    "source": "desidime",
    "image": "",
    "timestamp": "2026-04-17T16:55:48.170734+00:00"
  },
  {
    "text": "🔥LOOT BACK : Get 1 Month Amazon Prime Membership FREE \n\n✔️Pay ₹2 Using UPI or Bank Cards (Must Cancel auto-renew after using for few days)\n\n✔️PRIME MEMBERSHIP BENEFITS⬇️\n• Get Regular ₹1 Sample\n• Exclusive Discount & Cashback\n• Free Delivery & Fast Delivery \n• 24 Hrs Early Access an all Sales\n\n✨User specific...\n\n🎤If Offer Not Showing in Account, Check in New Account]\n\n🔗 https://tinyurl.com/2362vvkm\n\n🛒 Deals by @hugediscountshop",
    "url": "https://tinyurl.com/2362vvkm",
    "product_url": "https://www.amazon.in/amazonprime?primeCampaignId=prime_assoc_FT_IN&tag=lootdealska02-21",
    "source": "Loot_Deals_Xpress",
    "image": "",
    "timestamp": "2026-04-17T16:55:37.969212+00:00"
  },
  {
    "text": "Hair Root Touch Up Stick with Comb Applicator @160.\n\n🔗 https://tinyurl.com/2y5ndydr\n\n🛒 Deals by @hugediscountshop",
    "url": "https://tinyurl.com/2y5ndydr",
    "product_url": "https://www.amazon.in/dp/B0GWR8K87T?tag=Rickeykaran77-21",
    "source": "amazinglootsdealsoffers",
    "image": "",
    "timestamp": "2026-04-17T16:55:24.631007+00:00"
  },
  {
    "text": "Lowest : Samsung 25 W Charger at Rs.799\n\n🔗 https://tinyurl.com/26hvo83q\n\n🛒 Deals by @hugediscountshop",
    "url": "https://tinyurl.com/26hvo83q",
    "product_url": "https://linkredirect.in/visitretailer/2276?id=791399&shareid=g5dA8zU&dl=https%3A%2F%2Fwww.flipkart.com%2Fsamsung-25-w-gan-3-wall-charger-mobile%2Fp%2Fitm0341c57f94c47%3Fpid%3DACCHYG6CXZSZ5S7Z&source=Default",
    "source": "megadealind",
    "image": "",
    "timestamp": "2026-04-17T16:50:50.280206+00:00"
  },
  {
    "text": "Godrej Ezee Liquid Detergent for Semi-Automatic and Top Load Washers, 3.2kgs for ₹329.\n\n🔗 https://tinyurl.com/294obvkg\n\n🛒 Deals by @hugediscountshop",
    "url": "https://tinyurl.com/294obvkg",
    "product_url": "https://www.amazon.in/dp/B0DJPL5WX5?psc=1&th=1&tag=megadealind-21",
    "source": "megadealind",
    "image": "",
    "timestamp": "2026-04-17T16:50:43.279333+00:00"
  },
  {
    "text": "Lowest : Samsung 25 W Charger at Rs.799\n\n🔗 https://tinyurl.com/269gav47\n\n🛒 Deals by @hugediscountshop",
    "url": "https://tinyurl.com/269gav47",
    "product_url": "https://linkredirect.in/visitretailer/2276?id=791399&shareid=8VqJLjJ&dl=https%3A%2F%2Fwww.flipkart.com%2Fsamsung-25-w-gan-3-wall-charger-mobile%2Fp%2Fitm0341c57f94c47%3Fpid%3DACCHYG6CXZSZ5S7Z&source=Default",
    "source": "megadealind",
    "image": "",
    "timestamp": "2026-04-17T16:50:36.035015+00:00"
  },
  {
    "text": "Price Drop : Cuddles  Super Pants Baby Diaper L (62 Pieces) @ Rs.459\n\nSavings: Up to 60% Off Sizes: All sizes available (Newborn to XXL)\n\nGrab Your Bulk Packs While The Discount Is Still Live!\n\n🔗 https://tinyurl.com/2bdsk3rd\n\n🛒 Deals by @hugediscountshop",
    "url": "https://tinyurl.com/2bdsk3rd",
    "product_url": "https://linkredirect.in/visitretailer/2276?id=791399&shareid=gQedFp1&dl=https%3A%2F%2Fwww.flipkart.com%2Fe%2Fp%2Fp%3Fpid%3DDPRG6GR2ZJNRRVHU&source=Default",
    "source": "megadealind",
    "image": "",
    "timestamp": "2026-04-17T16:40:37.805479+00:00"
  },
  {
    "text": "Hisense 1.5 Ton 3 Star AC \n\nApply Rs.2000 Coupon + Pay Using SBI/ICICI 9M No Cost EMI\n\n🔗 https://tinyurl.com/282ngbl2\n\n🛒 Deals by @hugediscountshop",
    "url": "https://tinyurl.com/282ngbl2",
    "product_url": "https://linkredirect.in/visitretailer/2276?id=791399&shareid=TZSAhPk&dl=https%3A%2F%2Fwww.flipkart.com%2Fflipkart%2Fp%2Fitem%3Fpid%3DACNHJ9ZG9UC2ZPFU&source=Default",
    "source": "megadealind",
    "image": "",
    "timestamp": "2026-04-17T16:30:55.097887+00:00"
  },
  {
    "text": "Grab : Apple 20 W Original Charger at Rs.1599\n\n🔗 https://tinyurl.com/23rvjx3x\n\n🛒 Deals by @hugediscountshop",
    "url": "https://tinyurl.com/23rvjx3x",
    "product_url": "https://linkredirect.in/visitretailer/2276?id=791399&shareid=AojzfR0&dl=https%3A%2F%2Fwww.flipkart.com%2Fp%2Fp%2Fitmbd858702e076f%3Fpid%3DACCFWSKQJ8GS6DA7&source=Default",
    "source": "megadealind",
    "image": "",
    "timestamp": "2026-04-17T16:30:49.223032+00:00"
  },
  {
    "text": "Amazon Loot | 80% Off - Washing Machine Cleaner Tablets (pack of 25) Rs. 199 🧼✨ https://www.amazon.in/dp/B0GSRJXPX7?th=1&ck&tag=lootdealska02-21 🛒\n\n🔗 https://tinyurl.com/2de9nk6u\n\n🛒 Deals by @hugediscountshop",
    "url": "https://tinyurl.com/2de9nk6u",
    "product_url": "ttps://www.amazon.in/dp/B0GSRJXPX7?th=1&ck&tag=lootdealska02-21 ",
    "source": "Loot_Deals_Xpress",
    "image": "",
    "timestamp": "2026-04-17T16:30:39.373963+00:00"
  },
  {
    "text": "AMAZON LOOT\n\n🔥46% off : Biotique Green Apple Shine & Gloss Shampoo & Conditioner (650ml) At 360\n\n🔥42% Off : Herbal Essences Argan Oil Shampoo + Argan Oil Hair Mask  At 735\n\n🔗 https://tinyurl.com/29mv5rba\n\n🛒 Deals by @hugediscountshop",
    "url": "https://tinyurl.com/29mv5rba",
    "product_url": "https://www.amazon.in/dp/B07YWMQWWK?th=1&tag=megadealind-21",
    "source": "megadealind",
    "image": "",
    "timestamp": "2026-04-17T16:26:03.508371+00:00"
  },
  {
    "text": "REVLON Super Lustrous Matte Lipstick, 80% Conditioning Ingredients, intance color, Waterproof, Long-Lasting, 100% Vegan Lipstick, Sassy berry (437), 4.25 gm\n\n✅Deal Price: ₹ 199\n❌MRP: ₹ 999\nDiscount: 80%\n\n🔗 https://tinyurl.com/27o9mvac\n\n🛒 Deals by @hugediscountshop",
    "url": "https://tinyurl.com/27o9mvac",
    "product_url": "https://www.amazon.in/dp/B09CYJPYXM?tag=lootdealska02-21",
    "source": "Loot_Deals_Xpress",
    "image": "",
    "timestamp": "2026-04-17T16:25:47.031954+00:00"
  },
  {
    "text": "Orient Electric 9W Emergency LED Bulb| Rechargeable LED Light| 2 Hours Battery Backup| Up to 4 kV Surge Protection| 6500K, Cool White| B22d Base| Made in India| Pack of 1\n\n✅Deal Price: ₹ 243\n❌MRP: ₹ 2999\nDiscount: 92%\n\n🔗 https://tinyurl.com/25a3tpbw\n\n🛒 Deals by @hugediscountshop",
    "url": "https://tinyurl.com/25a3tpbw",
    "product_url": "https://www.amazon.in/dp/B0D8L86L32?tag=lootdealska02-21",
    "source": "Loot_Deals_Xpress",
    "image": "",
    "timestamp": "2026-04-17T16:25:37.687622+00:00"
  },
  {
    "text": "Outgeek Teeth Whitening Strips, Gentle for Sensitive Teeth, Professional Effect to Remove Stains, Teeth Whitening for Oral Care, 7 Treatment 14 Strips (7 Pairs)\n\n✅Deal Price: ₹ 139\n❌MRP: ₹ 699\nDiscount: 80%\n\n🔗 https://tinyurl.com/2dqmghlw\n\n🛒 Deals by @hugediscountshop",
    "url": "https://tinyurl.com/2dqmghlw",
    "product_url": "https://www.amazon.in/dp/B0989FHH5H?tag=lootdealska02-21",
    "source": "Loot_Deals_Xpress",
    "image": "",
    "timestamp": "2026-04-17T16:21:00.767291+00:00"
  },
  {
    "text": "JK Vision Smart WiFi Security Camera 1080P Full HD | 360° Pan 90° Tilt PTZ with Holder | Color Vision | Motion Detection Alert | Multi-User Sharing | Spotlight Function | Indoor CCTV.\n\n✅Deal Price: ₹ 980\n❌MRP: ₹ 5999\nDiscount: 84%\n\n🔗 https://tinyurl.com/2yq4hjxg\n\n🛒 Deals by @hugediscountshop",
    "url": "https://tinyurl.com/2yq4hjxg",
    "product_url": "https://www.amazon.in/dp/B0G4QSJ5B6?tag=lootdealska02-21",
    "source": "Loot_Deals_Xpress",
    "image": "",
    "timestamp": "2026-04-17T16:20:50.213080+00:00"
  },
  {
    "text": "Shoe Cleaning Wipes (80 Wipes) Instant Sneaker Cleaner Wipes for White Shoes | Quick Dirt & Stain Removal Sneaker Wipes | Portable Shoe Cleaner Wipes for Sports & Casual Footwear (Pack Of 1)\n\n✅Deal Price: ₹ 101\n❌MRP: ₹ 999\nDiscount: 90%\n\n🔗 https://tinyurl.com/25v62sbx\n\n🛒 Deals by @hugediscountshop",
    "url": "https://tinyurl.com/25v62sbx",
    "product_url": "https://www.amazon.in/dp/B0GS3BXW2C?tag=lootdealska02-21",
    "source": "Loot_Deals_Xpress",
    "image": "",
    "timestamp": "2026-04-17T16:20:38.991454+00:00"
  },
  {
    "text": "Lakme Forever Matte Liquid Lip Colour at Rs.157.\n\n🔗 https://tinyurl.com/2aoxp9xf\n\n🛒 Deals by @hugediscountshop",
    "url": "https://tinyurl.com/2aoxp9xf",
    "product_url": "https://www.amazon.in/dp/B0828W22T2?psc=1&th=1&tag=megadealind-21",
    "source": "megadealind",
    "image": "",
    "timestamp": "2026-04-17T16:15:58.533724+00:00"
  },
  {
    "text": "Amazon | UPTO 50% Off on Puma Slippers @ just ₹1019\n\n🔗 https://tinyurl.com/25yxvn3k\n\n🛒 Deals by @hugediscountshop",
    "url": "https://tinyurl.com/25yxvn3k",
    "product_url": "https://www.amazon.in/s?i=shoes&rh=n%3A1983396031%2Cp_36%3A100000-%2Cp_85%3A10440599031%2Cp_n_pct-off-with-tax%3A2665402031%2Cp_72%3A1318476031%2Cp_123%3A256097&s=price-asc-rank&dc&hidden-keywords=-Sponsored&_encoding=UTF8&content-id=amzn1.sym.d2818b63-f85c-4e08-9120-316bf273242c&pd_rd_r=b0369bbb-35a9-4eb1-9ee3-78bf5c7b1f59&pd_rd_w=AftzO&pd_rd_wg=e19MM&pf_rd_p=d2818b63-f85c-4e08-9120-316bf273242c&pf_rd_r=BP8ZM9QRQJJVZSPSHD7D&qid=1737264960&ds=v1%3AXWVbLjfW6CDd1F%2B%2BfmVkPQ4y5vUy1AF%2BzwSOJNcXQM4&ck&tag=lootdealska02-21",
    "source": "Loot_Deals_Xpress",
    "image": "",
    "timestamp": "2026-04-17T16:15:49.878872+00:00"
  },
  {
    "text": "Nirlon Brownie Granite 7-Piece Aluminum Non Stick Cookware Combo Gift Set (Compatible with Gas & stovetops)\n\n✅Deal Price: ₹ 1111\n❌MRP: ₹ 5625\nDiscount: 80%\n\n🔗 https://tinyurl.com/27n78wv7\n\n🛒 Deals by @hugediscountshop",
    "url": "https://tinyurl.com/27n78wv7",
    "product_url": "https://www.amazon.in/dp/B094QSY1NC?tag=lootdealska02-21",
    "source": "Loot_Deals_Xpress",
    "image": "",
    "timestamp": "2026-04-17T16:15:41.781106+00:00"
  },
  {
    "text": "Adhvik Small Size Ashok/Ashoka Sculpture Elegant Antique Office Table Décor & Handicraft Showpiece for Home and Car Dashboard\n\n✅Deal Price: ₹ 360\n❌MRP: ₹ 599\nDiscount: 40%\n\n🔗 https://tinyurl.com/243np2us\n\n🛒 Deals by @hugediscountshop",
    "url": "https://tinyurl.com/243np2us",
    "product_url": "https://www.amazon.in/dp/B0GCJS5S59?tag=lootdealska02-21",
    "source": "Loot_Deals_Xpress",
    "image": "",
    "timestamp": "2026-04-17T16:15:32.795146+00:00"
  },
  {
    "text": "Amazon | UPTO 50% Off on Puma Slippers @ just ₹1019\n\n🔗 https://tinyurl.com/2789ar7f\n\n🛒 Deals by @hugediscountshop",
    "url": "https://tinyurl.com/2789ar7f",
    "product_url": "https://www.amazon.in/s?i=shoes&rh=n%3A1983396031%2Cp_36%3A100000-%2Cp_85%3A10440599031%2Cp_n_pct-off-with-tax%3A2665402031%2Cp_72%3A1318476031%2Cp_123%3A256097&s=price-asc-rank&dc=&hidden-keywords=-Sponsored&content-id=amzn1.sym.d2818b63-f85c-4e08-9120-316bf273242c&pd_rd_r=b0369bbb-35a9-4eb1-9ee3-78bf5c7b1f59&pd_rd_w=AftzO&pd_rd_wg=e19MM&pf_rd_p=d2818b63-f85c-4e08-9120-316bf273242c&pf_rd_r=BP8ZM9QRQJJVZSPSHD7D&qid=1737264960&ds=v1%3AXWVbLjfW6CDd1F%2B%2BfmVkPQ4y5vUy1AF%2BzwSOJNcXQM4&tag=megadealind-21",
    "source": "megadealind",
    "image": "",
    "timestamp": "2026-04-17T16:11:33.732917+00:00"
  },
  {
    "text": "adidas Men Courun Avant M Running Shoe\n\n✅Deal Price: ₹ 1639\n❌MRP: ₹ 5599\nDiscount: 71%\n\n🔗 https://tinyurl.com/2572598f\n\n🛒 Deals by @hugediscountshop",
    "url": "https://tinyurl.com/2572598f",
    "product_url": "https://www.amazon.in/dp/B0C4DLTDWB?tag=lootdealska02-21",
    "source": "Loot_Deals_Xpress",
    "image": "",
    "timestamp": "2026-04-17T16:11:20.188584+00:00"
  },
  {
    "text": "Boniry Door Lock/Latch- Premium Door Locks for Main Door - High Security Main Door Latch for Home and Office - Durable and Reliable Door Latch for Enhanced Safety (Matt)\n\n✅Deal Price: ₹ 202\n❌MRP: ₹ 999\nDiscount: 80%\n\n🔗 https://tinyurl.com/2b56dgn9\n\n🛒 Deals by @hugediscountshop",
    "url": "https://tinyurl.com/2b56dgn9",
    "product_url": "https://www.amazon.in/dp/B0DRZSMX62?tag=lootdealska02-21",
    "source": "Loot_Deals_Xpress",
    "image": "",
    "timestamp": "2026-04-17T16:11:11.520725+00:00"
  },
  {
    "text": "French Connection Analog Watch for Women- FCN055A\n\n✅Deal Price: ₹ 939\n❌MRP: ₹ 6950\nDiscount: 86%\n\n🔗 https://tinyurl.com/2yes8ner\n\n🛒 Deals by @hugediscountshop",
    "url": "https://tinyurl.com/2yes8ner",
    "product_url": "https://www.amazon.in/dp/B0DP56Z5MY?tag=lootdealska02-21",
    "source": "Loot_Deals_Xpress",
    "image": "",
    "timestamp": "2026-04-17T16:11:01.637655+00:00"
  },
  {
    "text": "Whirlpool 2 Ton 3 Star, 3D cool Inverter Split AC (3D Cool 20T 3S INV EXP S6M3PP0, Copper, Convertible 4-in-1 Cooling Mode, HD Filter White, 2026 Model)\n\n✅Deal Price: ₹ 36990\n❌MRP: ₹ 70940\nDiscount: 48%\n\n🔗 https://tinyurl.com/24appuc9\n\n🛒 Deals by @hugediscountshop",
    "url": "https://tinyurl.com/24appuc9",
    "product_url": "https://www.amazon.in/dp/B0GHQRF65R?tag=lootdealska02-21",
    "source": "Loot_Deals_Xpress",
    "image": "",
    "timestamp": "2026-04-17T16:10:52.842157+00:00"
  },
  {
    "text": "Acer PowerHub Core GaN | 3 AC Outlets + 4 USB Ports | GaN Fast Charging 2500W @ 1,299₹\n\nRegular Price 1800\n\n🔗 https://tinyurl.com/244b4rna\n\n🛒 Deals by @hugediscountshop",
    "url": "https://tinyurl.com/244b4rna",
    "product_url": "https://www.amazon.in/dp/B0FDKYVCPP?tag=Rickeykaran77-21",
    "source": "amazinglootsdealsoffers",
    "image": "",
    "timestamp": "2026-04-17T16:10:40.351015+00:00"
  },
  {
    "text": "Loot Pack of 8 @ 249\n\n🔗 https://tinyurl.com/2b6waaug\n\n🛒 Deals by @hugediscountshop",
    "url": "https://tinyurl.com/2b6waaug",
    "product_url": "https://www.amazon.in/dp/B0GQ4F79TY?tag=Rickeykaran77-21",
    "source": "amazinglootsdealsoffers",
    "image": "",
    "timestamp": "2026-04-17T16:10:31.740503+00:00"
  },
  {
    "text": "Amazon : Upto 77% off on Beardo Perfumes \n\n75% off : BEARDO Perfumes — Pack of 4 @ ₹912\n64% off :Whisky Smoke + Godfather (2-Pack) @ ₹500\n68% off : Day Perfumes — 4 × 20ml @ ₹384\n\nMore Offers\n\n🔗 https://tinyurl.com/2cfkpw29\n\n🛒 Deals by @hugediscountshop",
    "url": "https://tinyurl.com/2cfkpw29",
    "product_url": "https://www.amazon.in/dp/B0DZXX8XN5?th=1&tag=megadealind-21",
    "source": "megadealind",
    "image": "",
    "timestamp": "2026-04-17T16:06:19.806013+00:00"
  },
  {
    "text": "Fk Minutes Loot : Philips New Launch Powerbank Starts @1249.\n\n🔗 https://tinyurl.com/2d9oj9av\n\n🛒 Deals by @hugediscountshop",
    "url": "https://tinyurl.com/2d9oj9av",
    "product_url": "https://linkredirect.in/visitretailer/2276?id=791399&shareid=o5aGKem&dl=https%3A%2F%2Fwww.flipkart.com%2Ftyy%2F4mr%2Ffu6%2F~cs-7whemydhnt%2Fpr%3Fsid%3Dtyy%252C4mr%252Cfu6%26marketplace%3DHYPERLOCAL%26collection-tab-name%3DPhilips%2Bpowerbank%26sort%3Dprice_asc%26pageUID%3D1776439097584&source=Default",
    "source": "megadealind",
    "image": "",
    "timestamp": "2026-04-17T16:06:07.816106+00:00"
  },
  {
    "text": "Dabur Himalayan Shilajit/Shilajeet Resin - 30g (15g x 2) | 250mg per serving | Boosts Muscle Growth & Stamina | 100% Ayurvedic | Grade A shilajit sourced from the Himalayas up to 19,000 ft\n\n✅Deal Price: ₹ 710\n❌MRP: ₹ 2900\nDiscount: 76%\n\n🔗 https://tinyurl.com/23l7c5cn\n\n🛒 Deals by @hugediscountshop",
    "url": "https://tinyurl.com/23l7c5cn",
    "product_url": "https://www.amazon.in/dp/B0CN9C1WD4?tag=lootdealska02-21",
    "source": "Loot_Deals_Xpress",
    "image": "",
    "timestamp": "2026-04-17T16:05:54.437639+00:00"
  },
  {
    "text": "Boniry Space Aluminium Tissue Paper Roll Holder Kitchen and Bathroom/Tissue Paper Roll Stand/Bathroom and Kitchen Accessories (Black) (1 PCS)\n\n✅Deal Price: ₹ 306\n❌MRP: ₹ 1499\nDiscount: 80%\n\n🔗 https://tinyurl.com/284b53d7\n\n🛒 Deals by @hugediscountshop",
    "url": "https://tinyurl.com/284b53d7",
    "product_url": "https://www.amazon.in/dp/B0DHCQBFC3?tag=lootdealska02-21",
    "source": "Loot_Deals_Xpress",
    "image": "",
    "timestamp": "2026-04-17T16:05:45.608684+00:00"
  },
  {
    "text": "Amazon : Upto 77% off on Beardo Perfumes \n\n75% off : BEARDO Perfumes — Pack of 4 @ ₹912\n64% off :Whisky Smoke + Godfather (2-Pack) @ ₹500\n68% off : Day Perfumes — 4 × 20ml @ ₹384\n\nMore Offers\n\n🔗 https://tinyurl.com/2cfkpw29\n\n🛒 Deals by @hugediscountshop",
    "url": "https://tinyurl.com/2cfkpw29",
    "product_url": "https://www.amazon.in/dp/B0DZXX8XN5?th=1&ck&tag=lootdealska02-21",
    "source": "Loot_Deals_Xpress",
    "image": "",
    "timestamp": "2026-04-17T16:05:35.411292+00:00"
  },
  {
    "text": "French Essence Noir| Deodorant for Men and Women | Body Spray | Long Lasting Scent - 150ml Pack of 3\n\n✅Deal Price: ₹ 299\n❌MRP: ₹ 675\nDiscount: 56%\n\n🔗 https://tinyurl.com/2398q7m8\n\n🛒 Deals by @hugediscountshop",
    "url": "https://tinyurl.com/2398q7m8",
    "product_url": "https://www.amazon.in/dp/B0C85JHGZS?tag=lootdealska02-21",
    "source": "Loot_Deals_Xpress",
    "image": "",
    "timestamp": "2026-04-17T16:01:20.798068+00:00"
  },
  {
    "text": ".\n\nGrab 🔥 \n1,648₹\nCoupon \n\nRR Signature 1200 MM Wavia High Speed Ceiling Fan\n\n🔗 https://tinyurl.com/293vfbht\n\n🛒 Deals by @hugediscountshop",
    "url": "https://tinyurl.com/293vfbht",
    "product_url": "https://www.amazon.in/dp/B0D5H6XNMY?th=1&ck&tag=lootdealska02-21",
    "source": "Loot_Deals_Xpress",
    "image": "",
    "timestamp": "2026-04-17T16:01:10.085954+00:00"
  },
  {
    "text": "Pigeon Stainless Steel Inox Hydra Plus 900Ml Pack Of 3,Silver\n\n✅Deal Price: ₹ 509\n❌MRP: ₹ 1495\nDiscount: 66%\n\n🔗 https://tinyurl.com/2c365yz6\n\n🛒 Deals by @hugediscountshop",
    "url": "https://tinyurl.com/2c365yz6",
    "product_url": "https://www.amazon.in/dp/B0BYZJDQDD?tag=lootdealska02-21",
    "source": "Loot_Deals_Xpress",
    "image": "",
    "timestamp": "2026-04-17T16:01:00.080869+00:00"
  },
  {
    "text": "Evereve Teens Period Panties, S-M, 5Pcs Pack of 2 (for 13-19 yrs old), 360° Anti-Leak Protection, up to 12hrs Absorbency, Heavy Flow Care, Ideal for School & Overnight Use, Comfy Hug Fit\n\n✅Deal Price: ₹ 189\n❌MRP: ₹ 274\nDiscount: 31%\n\n🔗 https://tinyurl.com/24tlhog4\n\n🛒 Deals by @hugediscountshop",
    "url": "https://tinyurl.com/24tlhog4",
    "product_url": "https://www.amazon.in/dp/B0FR26FKG4?tag=lootdealska02-21",
    "source": "Loot_Deals_Xpress",
    "image": "",
    "timestamp": "2026-04-17T16:00:49.160827+00:00"
  },
  {
    "text": "Mamaearth Into The Valley Liquid Eau De Parfum For Women-100Ml|Made Safe Approved|Premium&Long-Lasting Fragrance|Blend Of Exotic Ingredients|Perfume With Pear,Jasmine&Vanilla Notes|Fresh Scent\n\n✅Deal Price: ₹ 359\n❌MRP: ₹ 899\nDiscount: 60%\n\n🔗 https://tinyurl.com/27z36qqt\n\n🛒 Deals by @hugediscountshop",
    "url": "https://tinyurl.com/27z36qqt",
    "product_url": "https://www.amazon.in/dp/B0D6RR33F3?tag=lootdealska02-21",
    "source": "Loot_Deals_Xpress",
    "image": "",
    "timestamp": "2026-04-17T15:55:45.342528+00:00"
  },
  {
    "text": "essence Soft & Precise Lip Pencil - 202 My Mind (0.78 g)\n\n✅Deal Price: ₹ 88\n❌MRP: ₹ 275\nDiscount: 68%\n\n🔗 https://tinyurl.com/27foyo93\n\n🛒 Deals by @hugediscountshop",
    "url": "https://tinyurl.com/27foyo93",
    "product_url": "https://www.amazon.in/dp/B09HHC77ZX?tag=lootdealska02-21",
    "source": "Loot_Deals_Xpress",
    "image": "",
    "timestamp": "2026-04-17T15:55:32.405296+00:00"
  },
  {
    "text": "Loot: Himalayan Shilajit Resin 10g at ₹349\n\nApply ₹250 Off Coupon\n\n🔗 https://tinyurl.com/2acv99zq\n\n🛒 Deals by @hugediscountshop",
    "url": "https://tinyurl.com/2acv99zq",
    "product_url": "https://www.amazon.in/dp/B0G64J8GJW?tag=megadealind-21",
    "source": "megadealind",
    "image": "",
    "timestamp": "2026-04-17T15:51:08.322933+00:00"
  },
  {
    "text": "Philips 0.5W LED Red Bulb, Pack of 1 (Joy Vision, Prong)\n\n✅Deal Price: ₹ 79\n❌MRP: ₹ 150\nDiscount: 47%\n\n🔗 https://tinyurl.com/22u7mjap\n\n🛒 Deals by @hugediscountshop",
    "url": "https://tinyurl.com/22u7mjap",
    "product_url": "https://www.amazon.in/dp/B00Q2RGP5O?tag=lootdealska02-21",
    "source": "Loot_Deals_Xpress",
    "image": "",
    "timestamp": "2026-04-17T15:50:55.900580+00:00"
  },
  {
    "text": "Beco Eco Friendly Compostable Garbage Bags for Dustbin | 30 Pcs | Small 17 X 19 Inches | Pack of 2\n\n✅Deal Price: ₹ 119\n❌MRP: ₹ 260\nDiscount: 54%\n\n🔗 https://tinyurl.com/29t7zxnt\n\n🛒 Deals by @hugediscountshop",
    "url": "https://tinyurl.com/29t7zxnt",
    "product_url": "https://www.amazon.in/dp/B0C65BCWRZ?tag=lootdealska02-21",
    "source": "Loot_Deals_Xpress",
    "image": "",
    "timestamp": "2026-04-17T15:50:47.496534+00:00"
  },
  {
    "text": "amazon basics Quad Pro 4-in-1 Metal Flat Braided Indestructible Smartphone Usb Cable (1.5m, 60W) Ultimate All-in-One Charging Solution, Black\n\n✅Deal Price: ₹ 229\n❌MRP: ₹ 999\nDiscount: 77%\n\n🔗 https://tinyurl.com/2ac6h7xv\n\n🛒 Deals by @hugediscountshop",
    "url": "https://tinyurl.com/2ac6h7xv",
    "product_url": "https://www.amazon.in/dp/B0DK9H4TMW?tag=lootdealska02-21",
    "source": "Loot_Deals_Xpress",
    "image": "",
    "timestamp": "2026-04-17T15:50:37.091292+00:00"
  },
  {
    "text": "GIGABYTE GV-N506TWF2OC-8GD | GeForce RTX 5060 Ti WINDFORCE 2X OC 8GB GDDR6 Graphics Card\n\n✅Deal Price: ₹ 46972\n❌MRP: ₹ 155750\nDiscount: 70%\n\n🔗 https://tinyurl.com/28ox8br5\n\n🛒 Deals by @hugediscountshop",
    "url": "https://tinyurl.com/28ox8br5",
    "product_url": "https://www.amazon.in/dp/B0F4ZFPVC1?tag=lootdealska02-21",
    "source": "Loot_Deals_Xpress",
    "image": "",
    "timestamp": "2026-04-17T15:45:56.109175+00:00"
  },
  {
    "text": "🔥🔥ApTechDeals HTC-1 Digital Hygrometer Thermometer Humidity Meter With Clock LCD Display\n\n🎁 Deal Price : ₹286\n\n🔗 https://tinyurl.com/2yrtt5ea\n\n🛒 Deals by @hugediscountshop",
    "url": "https://tinyurl.com/2yrtt5ea",
    "product_url": "https://www.amazon.in/dp/B07V1GJFK5?th=1&ck&tag=lootdealska02-21",
    "source": "Loot_Deals_Xpress",
    "image": "",
    "timestamp": "2026-04-17T15:45:47.523132+00:00"
  },
  {
    "text": "Amazon Basics Pro Series 4-in-1 USB-C Hub, and USB-A 3.2 Gen 2 HighSpeed Data Transfer(Up to10Gbps) - Compact and Versatile Hub for PC,MacBook,Laptops, hones, Monitors, and Projectors (Turquoise)|portable\n\n✅Deal Price: ₹ 585\n❌MRP: ₹ 3999\nDiscount: 85%\n\n🔗 https://tinyurl.com/2ct2otd6\n\n🛒 Deals by @hugediscountshop",
    "url": "https://tinyurl.com/2ct2otd6",
    "product_url": "https://www.amazon.in/dp/B0DPCR5DXJ?tag=lootdealska02-21",
    "source": "Loot_Deals_Xpress",
    "image": "",
    "timestamp": "2026-04-17T15:45:36.002667+00:00"
  },
  {
    "text": "🔥🔥\n265₹\n\nNIVEA Derma Skin Clear Wash Gel (150ml)\n\n🔗 https://tinyurl.com/22ndb8ag\n\n🛒 Deals by @hugediscountshop",
    "url": "https://tinyurl.com/22ndb8ag",
    "product_url": "https://www.amazon.in/dp/B0B978RVMF?ck&tag=lootdealska02-21",
    "source": "Loot_Deals_Xpress",
    "image": "",
    "timestamp": "2026-04-17T15:41:04.899623+00:00"
  },
  {
    "text": "Orient Electric Elfie Rechargeable Personal Fan | 90° Adjustable Airflow | 1800 mAh Battery | 4 Speed Modes | Quiet Operation | USB Type-C Charging | Compact Mini Fan (White)\n\n✅Deal Price: ₹ 999\n❌MRP: ₹ 2500\nDiscount: 60%\n\n🔗 https://tinyurl.com/2y48j9ax\n\n🛒 Deals by @hugediscountshop",
    "url": "https://tinyurl.com/2y48j9ax",
    "product_url": "https://www.amazon.in/dp/B0FJ1GNT5F?tag=lootdealska02-21",
    "source": "Loot_Deals_Xpress",
    "image": "",
    "timestamp": "2026-04-17T15:40:53.889376+00:00"
  },
  {
    "text": "Boat Nirvana Iris Truly Wireless in Ear Ear Buds w/Up to 32 dB Active Noise Cancellation,120 Hrs Playback,Crystal Bionic Sound Powered by HiFi,Beast Mode,ENx Tech,Hearables App(Crystal Black)\n\n✅Deal Price: ₹ 1899\n❌MRP: ₹ 9990\nDiscount: 81%\n\n🔗 https://tinyurl.com/2a3jfnuf\n\n🛒 Deals by @hugediscountshop",
    "url": "https://tinyurl.com/2a3jfnuf",
    "product_url": "https://www.amazon.in/dp/B0DN1JF7JY?tag=lootdealska02-21",
    "source": "Loot_Deals_Xpress",
    "image": "",
    "timestamp": "2026-04-17T15:40:45.053431+00:00"
  },
  {
    "text": ".\n\nAnt Esports LED Keyboard and Mouse Combo\n\n798₹\n\n🔗 https://tinyurl.com/28xn3e9q\n\n🛒 Deals by @hugediscountshop",
    "url": "https://tinyurl.com/28xn3e9q",
    "product_url": "https://www.amazon.in/dp/B0CMXQN2B4?ck&tag=lootdealska02-21",
    "source": "Loot_Deals_Xpress",
    "image": "",
    "timestamp": "2026-04-17T15:40:38.449780+00:00"
  },
  {
    "text": "LuvLap Baby Lotion with Milk Protein - 400ml, Gentle Daily Lotion for Face & Body, 24 Hour Protection for Sensitive Skin, Ph 5.5, Shea Butter and VIT E, Paraben Free, Dermatologically Tested\n\n✅Deal Price: ₹ 116\n❌MRP: ₹ 290\nDiscount: 60%\n\n🔗 https://tinyurl.com/29qv5j7z\n\n🛒 Deals by @hugediscountshop",
    "url": "https://tinyurl.com/29qv5j7z",
    "product_url": "https://www.amazon.in/dp/B0FGJX1TCN?tag=lootdealska02-21",
    "source": "Loot_Deals_Xpress",
    "image": "",
    "timestamp": "2026-04-17T15:40:31.554446+00:00"
  },
  {
    "text": "Hitachi 1.5 Ton 3 Star Split AC \n\nApply ₹500 Off Coupon + ₹6250 Off With HDFC Credit Card\n\n🔗 https://tinyurl.com/27p8a2dz\n\n🛒 Deals by @hugediscountshop",
    "url": "https://tinyurl.com/27p8a2dz",
    "product_url": "https://www.amazon.in/dp/B0GP71KXP5?psc=1&th=1&tag=megadealind-21",
    "source": "megadealind",
    "image": "",
    "timestamp": "2026-04-17T15:36:17.362820+00:00"
  },
  {
    "text": "Price Drop On Premium Mobile Covers Starts @501.\n\n🔗 https://tinyurl.com/24vpystt\n\n🛒 Deals by @hugediscountshop",
    "url": "https://tinyurl.com/24vpystt",
    "product_url": "https://linkredirect.in/visitretailer/2276?id=791399&shareid=6tL20SP&dl=https%3A%2F%2Fwww.flipkart.com%2Ftyy%2F4mr%2Fq2u%2F~cs-h84be4j19z%2Fpr%3Fsid%3Dtyy%252C4mr%252Cq2u%26collection-tab-name%3DSpigen%2Bcovers%26sort%3Dprice_asc&source=Default",
    "source": "megadealind",
    "image": "",
    "timestamp": "2026-04-17T15:36:09.972176+00:00"
  },
  {
    "text": "🔥🔥\n299₹\n\nBagrry's Crunchy Dark Chocolate Muesli 700g / 750g\n\n🔗 https://tinyurl.com/26z6rq2u\n\n🛒 Deals by @hugediscountshop",
    "url": "https://tinyurl.com/26z6rq2u",
    "product_url": "https://www.amazon.in/dp/B00LA5OGXG?th=1&ck&tag=lootdealska02-21",
    "source": "Loot_Deals_Xpress",
    "image": "",
    "timestamp": "2026-04-17T15:36:00.216659+00:00"
  },
  {
    "text": "Yogabar Whole Quinoa 1kg Pouch - Gluten Free Quinoa Grain - Diet Food for Weight Loss Management - Helps Manage Sugar Levels - Low GI for sustained Energy\n\n✅Deal Price: ₹ 199\n❌MRP: ₹ 499\nDiscount: 60%\n\n🔗 https://tinyurl.com/2dhcsxb2\n\n🛒 Deals by @hugediscountshop",
    "url": "https://tinyurl.com/2dhcsxb2",
    "product_url": "https://www.amazon.in/dp/B0D1C8RQTV?tag=lootdealska02-21",
    "source": "Loot_Deals_Xpress",
    "image": "",
    "timestamp": "2026-04-17T15:35:51.042858+00:00"
  },
  {
    "text": "Little's Organix Gentle Baby Detergent Liquid for Clothes | 1000 ml x Refill | Anti-Bacterial Liquid Detergent for Baby Clothes Enriched with Aloe Vera & Neem Extracts | Free from Brighteners & Bleach\n\n✅Deal Price: ₹ 229\n❌MRP: ₹ 425\nDiscount: 46%\n\n🔗 https://tinyurl.com/27lnds2l\n\n🛒 Deals by @hugediscountshop",
    "url": "https://tinyurl.com/27lnds2l",
    "product_url": "https://www.amazon.in/dp/B0CTTMJPC9?tag=lootdealska02-21",
    "source": "Loot_Deals_Xpress",
    "image": "",
    "timestamp": "2026-04-17T15:35:41.237361+00:00"
  },
  {
    "text": "NIVEA Derma Skin Clear Wash Gel (150ml), Deep Cleansing Face Wash Gel, Salicylic Acid Face Wash Enriched with Niacinamide to Cleanse Pores and Remove Impurities\n\n✅Deal Price: ₹ 265\n❌MRP: ₹ 669\nDiscount: 60%\n\n🔗 https://tinyurl.com/22ndb8ag\n\n🛒 Deals by @hugediscountshop",
    "url": "https://tinyurl.com/22ndb8ag",
    "product_url": "https://www.amazon.in/dp/B0B978RVMF?tag=lootdealska02-21",
    "source": "Loot_Deals_Xpress",
    "image": "",
    "timestamp": "2026-04-17T15:35:31.566413+00:00"
  },
  {
    "text": "Revlon Colorstay Gel Envy Diamond Top Coat (11.7ml)\n\n✅Deal Price: ₹ 149\n❌MRP: ₹ 599\nDiscount: 75%\n\n🔗 https://tinyurl.com/24vyrnq3\n\n🛒 Deals by @hugediscountshop",
    "url": "https://tinyurl.com/24vyrnq3",
    "product_url": "https://www.amazon.in/dp/B00TIOO2WG?tag=lootdealska02-21",
    "source": "Loot_Deals_Xpress",
    "image": "",
    "timestamp": "2026-04-17T15:30:53.533628+00:00"
  },
  {
    "text": "FAAST 💥 \n299₹\nWomen's Clothing\n\n🔗 https://tinyurl.com/29u8l6pg\n\n🛒 Deals by @hugediscountshop",
    "url": "https://tinyurl.com/29u8l6pg",
    "product_url": "https://www.amazon.in/s?k=AKA%2520CHIC%2520Skinny%2520Women%2520Jeans&i=apparel&s=price-asc-rank&ds=v1%253A21TJWha1yNQE%2520IvW%2520P0UPgPmM23s8mM4SBFdjxsyrUI&crid=2VUCDSLG58BLG&item=B07ZVS9BBH&qid=1759230132&sprefix=aka%2520chic%2520skinny%2520women%2520jeans%252Capparel%252C259&ck&tag=lootdealska02-21",
    "source": "Loot_Deals_Xpress",
    "image": "",
    "timestamp": "2026-04-17T15:30:44.750637+00:00"
  },
  {
    "text": "Moody DermaSoothe Brightening Face Mist & Essence Toner with Rice & Ceramides | Strenghten Skin Barrier | For Clear, Glass Korean Skin, Bright & Hydrated Skin | Alcohol-Free Toner | Women & Men | 110ml\n\n✅Deal Price: ₹ 123\n❌MRP: ₹ 249\nDiscount: 51%\n\n🔗 https://tinyurl.com/27h5h7ty\n\n🛒 Deals by @hugediscountshop",
    "url": "https://tinyurl.com/27h5h7ty",
    "product_url": "https://www.amazon.in/dp/B0CNWCDZXH?tag=lootdealska02-21",
    "source": "Loot_Deals_Xpress",
    "image": "",
    "timestamp": "2026-04-17T15:30:39.824487+00:00"
  },
  {
    "text": "Vishudh Women ROUND NECK ETHNIC SET VNK3007600\n\n✅Deal Price: ₹ 322\n❌MRP: ₹ 3249\nDiscount: 90%\n\n🔗 https://tinyurl.com/2cw7wyal\n\n🛒 Deals by @hugediscountshop",
    "url": "https://tinyurl.com/2cw7wyal",
    "product_url": "https://www.amazon.in/dp/B0FGVF96S4?tag=lootdealska02-21",
    "source": "Loot_Deals_Xpress",
    "image": "",
    "timestamp": "2026-04-17T15:25:58.810766+00:00"
  },
  {
    "text": "🔥🔥Boldfit Heavy Resistance Band for Workout Set Exercise\n\n🎁 Deal Price : ₹167\n\n⚡⚡Apply 3% Coupon (Prime Discount)\n\n🔗 https://tinyurl.com/2bk5aceb\n\n🛒 Deals by @hugediscountshop",
    "url": "https://tinyurl.com/2bk5aceb",
    "product_url": "https://www.amazon.in/dp/B08H8KD72Q?th=1&ck&tag=lootdealska02-21",
    "source": "Loot_Deals_Xpress",
    "image": "",
    "timestamp": "2026-04-17T15:25:52.088141+00:00"
  },
  {
    "text": "🔥🔥\n1,299₹\n\nAcer PowerHub Core GaN | 3 AC Outlets + 4 USB Ports (2 Type-C GaN PD 65W + 2 Type-A) | GaN Fast Charging 2500W\n\n🔗 https://tinyurl.com/244b4rna\n\n🛒 Deals by @hugediscountshop",
    "url": "https://tinyurl.com/244b4rna",
    "product_url": "https://www.amazon.in/dp/B0FDKYVCPP?ck&tag=lootdealska02-21",
    "source": "Loot_Deals_Xpress",
    "image": "",
    "timestamp": "2026-04-17T15:25:42.549863+00:00"
  },
  {
    "text": "GO DESi - Gulab Jamun | Made with Pure Cow Ghee | Indian Mithai | Classic sweets | Sweets Gift Pack | 500 grams\n\n✅Deal Price: ₹ 170\n❌MRP: ₹ 199\nDiscount: 15%\n\n🔗 https://tinyurl.com/2y9pv6gr\n\n🛒 Deals by @hugediscountshop",
    "url": "https://tinyurl.com/2y9pv6gr",
    "product_url": "https://www.amazon.in/dp/B0GMJQCN8C?tag=lootdealska02-21",
    "source": "Loot_Deals_Xpress",
    "image": "",
    "timestamp": "2026-04-17T15:25:33.026044+00:00"
  },
  {
    "text": "Wonderize Dry Comfort Sanitary Napkins for Women – Regular 230mm, Super Saver Pack, 40 Pads (Combo of 2)\n\n✅Deal Price: ₹ 185\n❌MRP: ₹ 363\nDiscount: 49%\n\n🔗 https://tinyurl.com/2yn4t73g\n\n🛒 Deals by @hugediscountshop",
    "url": "https://tinyurl.com/2yn4t73g",
    "product_url": "https://www.amazon.in/dp/B07KMYJ7L8?tag=lootdealska02-21",
    "source": "Loot_Deals_Xpress",
    "image": "",
    "timestamp": "2026-04-17T15:21:11.092112+00:00"
  },
  {
    "text": "🔥🔥Dyazo Laptop Cooling Pad |Laptop Stand with Cooling Fan\n\n🎁 Deal Price : ₹513\n\n⚡⚡Apply 3% Coupon (Prime Discount)\n\n🔗 https://tinyurl.com/22lw9t6g\n\n🛒 Deals by @hugediscountshop",
    "url": "https://tinyurl.com/22lw9t6g",
    "product_url": "https://www.amazon.in/dp/B0CRZBR52Y?th=1&ck&tag=lootdealska02-21",
    "source": "Loot_Deals_Xpress",
    "image": "",
    "timestamp": "2026-04-17T15:21:01.863027+00:00"
  }
]